Workbook

Sheet Start Here
B2: CPARS Playbook: How Ratings Get Decided, and How to Earn the One You Want
B3: For contractors. The rating you get at the end of the period is decided by what is on file during the period. This workbook is how you build that file.
B5: How CPARS actually works
B6: Your Contracting Officer’s Representative or Assessing Official drafts a rating in each evaluation area, on a five-point scale defined in FAR 42.1503: Exceptional, Very Good, Satisfactory, Marginal, Unsatisfactory. The Contracting Officer reviews it. You are notified and have 14 calendar days to comment. If you disagree, you may request review by a Government official one level above the Contracting Officer. The final rating stays in the system for three years and is visible to every source selection you bid on.
B7: The part most contractors get wrong: Satisfactory means you met the contract. Very Good and Exceptional require documented performance that exceeded requirements to the Government’s benefit, and the Assessing Official has to be able to write down what that was. If you did not give them the words and the evidence during the period, you will get Satisfactory, and Satisfactory loses recompetes.
B9: The tabs
B10: 1. Rating Decoder: what each rating means in each area, what the Assessing Official needs to see to justify it, and why contractors who deserved Very Good got Satisfactory.
B11: 2. Evidence Log: a dated record of performance events, positive and negative, by area. This is the file. Keep it monthly.
B12: 3. Self-Assessment: rate yourself by area against the definitions, with evidence counts pulled from the log. Predicts your rating before the draft arrives.
B13: 4. Interim Check-In: the questions to ask your COR at the mid-point so the final rating is not a surprise, and a place to record the answers.
B14: 5. Rebuttal Builder: if the draft is wrong, a structured 14-day response: the requirement, the evidence, the rating sought, and the language. What to argue and what not to.
B16: Where this is taught
... B23: Licensed for one contract or one organization. Customize freely. Company-wide deployment or resale requires an Acqlerate Team License (acqlerate.com/team).

Sheet Rating Decoder
B2: Rating Decoder: What Each Rating Requires, by Area
B3: The FAR definition is one column. What the Assessing Official actually has to be able to write down is the other. The gap between them is where Very Good becomes Satisfactory.
B5: Area | C5: Rating | D5: What FAR 42.1503 says | E5: What the AO has to be able to write down | F5: Why deserving contractors get the rating below
B6: Quality | C6: Exceptional | D6: Performance meets contractual requirements and exceeds many to the Government’s benefit. No significant weaknesses. | E6: Specific deliverables or outcomes that exceeded the spec, with a measured benefit: defect rates below the requirement by a stated margin, rework avoided, customer time saved. Several instances, not one. | F6: The AO agrees you were excellent but cannot cite the specific instances, because you never wrote them down and sent them. Exceptional needs a list.
B7: Quality | C7: Very Good | D7: Performance meets contractual requirements and exceeds some to the Government’s benefit. No significant weaknesses. | E7: At least a few named instances where quality exceeded the requirement, with a benefit the AO can describe in a sentence. Zero significant quality findings. | F7: You exceeded requirements but nobody told the COR at the time. Six months later it reads as "did the job." Very Good needs contemporaneous evidence.
B8: Quality | C8: Satisfactory | D8: Performance meets contractual requirements. Minor problems, if any, and corrective actions were effective. | E8: Deliverables accepted. Any rejections were corrected promptly. No pattern. | F8: You met the contract. This is the rating for meeting the contract. It is not a criticism; it is also not a discriminator on the next bid.
B9: Quality | C9: Marginal | D9: Performance does not meet some contractual requirements. A significant weakness that corrective action has not yet fixed. | E9: A rejected deliverable or quality finding that was not fully corrected in the period. | F9: A single significant problem that you fixed, but the fix landed after the rating period closed. Timing matters.
B10: Quality | C10: Unsatisfactory | D10: Performance does not meet most contractual requirements. Serious problems; corrective actions ineffective. | E10: Repeated rejections; a corrective action plan that did not work. | F10: Usually not a surprise. If it is, the interim check-in was skipped.
B11: Schedule | C11: Exceptional | D11: Performance meets contractual requirements and exceeds many to the Government’s benefit. No significant weaknesses. | E11: Milestones delivered early with a stated benefit to the Government (earlier fielding, freed resources). Proactive schedule risk management the AO witnessed. | F11: The AO agrees you were excellent but cannot cite the specific instances, because you never wrote them down and sent them. Exceptional needs a list.
B12: Schedule | C12: Very Good | D12: Performance meets contractual requirements and exceeds some to the Government’s benefit. No significant weaknesses. | E12: All milestones on time, some early. Schedule risks identified by you before the Government saw them. | F12: You exceeded requirements but nobody told the COR at the time. Six months later it reads as "did the job." Very Good needs contemporaneous evidence.
B13: Schedule | C13: Satisfactory | D13: Performance meets contractual requirements. Minor problems, if any, and corrective actions were effective. | E13: Milestones met. Any slip was recovered and did not affect the Government. | F13: You met the contract. This is the rating for meeting the contract. It is not a criticism; it is also not a discriminator on the next bid.
B14: Schedule | C14: Marginal | D14: Performance does not meet some contractual requirements. A significant weakness that corrective action has not yet fixed. | E14: A missed milestone that affected the Government, with recovery still in progress. | F14: A single significant problem that you fixed, but the fix landed after the rating period closed. Timing matters.
B15: Schedule | C15: Unsatisfactory | D15: Performance does not meet most contractual requirements. Serious problems; corrective actions ineffective. | E15: Multiple missed milestones; Government mission affected. | F15: Usually not a surprise. If it is, the interim check-in was skipped.
B16: Cost Control | C16: Exceptional | D16: Performance meets contractual requirements and exceeds many to the Government’s benefit. No significant weaknesses. | E16: Underran with documented savings returned or repurposed. Cost data timely and accurate every period. Cost-saving initiatives you proposed and the Government accepted. | F16: The AO agrees you were excellent but cannot cite the specific instances, because you never wrote them down and sent them. Exceptional needs a list.
... B35: Regulatory Compliance | C35: Unsatisfactory | D35: Performance does not meet most contractual requirements. Serious problems; corrective actions ineffective. | E35: Uncorrected compliance failure or a finding with contractual consequence. | F35: Usually not a surprise. If it is, the interim check-in was skipped.
B37: Acqlerate CPARS Playbook · acqlerate.com · September 2026 Edition

Sheet Evidence Log
B2: Evidence Log: The File That Decides Your Rating
B3: One row per performance event, positive or negative. Send the positive ones to your COR when they happen. Fix and close the negative ones before the period ends. Monthly, minimum.
B5: Date | C5: Area | D5: + / − | E5: What happened (specific, measurable) | F5: Benefit to the Government / impact | G5: Shared with COR? | H5: Documented where | I5: Status
B6: 46217 | C6: Schedule | D6: + | E6: Delivered Increment 2 test readiness package 9 working days ahead of the CDRL due date. | F6: Government test team started dry runs a week early; freed range time worth an estimated $40K. | G6: Yes | H6: Email to COR 7/14; CDRL A012 transmittal | I6: Closed
B7: 46231 | C7: Quality | D7: + | E7: Zero defects on Increment 2 software acceptance testing, 412 test cases. | F7: No rework cycle; acceptance signed same day. | G7: Yes | H7: Test report TR-2026-07 | I7: Closed
B8: 46239 | C8: Management | D8: − | E8: Deputy PM resigned; position vacant. | F8: Risk to schedule reviews and stakeholder communication. | G8: Yes | H8: Letter to CO 8/6; resolved 8/19 | I8: Closed
B9: 46253 | C9: Management | D9: + | E9: Deputy PM backfilled within 10 business days with candidate meeting all key personnel qualifications; CO approved substitution. | F9: No gap in program reviews; Government did not have to intervene. | G9: Yes | H9: CO approval 8/19 | I9: Closed
B10: 46264 | C10: Cost Control | D10: + | E10: Identified $85K underrun in Year 2 travel; proposed repurposing to accelerate Increment 3 tooling. Government accepted. | F10: Increment 3 tooling delivered a quarter early at no added cost. | G10: Yes | H10: Mod P00007 | I10: Closed
B11: 46268 | C11: Regulatory Compliance | D11: + | E11: Posted a current CMMC Level 2 self-assessment in SPRS and closed the last POA&M item 40 days early; confirmed both CUI-handling subcontractors are current. | F11: CO's SPRS check before the option exercise came back clean; the Government did not have to follow up. | G11: Yes | H11: Assessment certificate; email to COR 9/3 | I11: Closed
B47: TALLY BY AREA
B48: Area | C48: Positive | D48: Negative | E48: Neg. still open | F48: Positive not yet shared
B49: Quality | C49: =COUNTIFS($C$6:$C$45,$B49,$D$6:$D$45,"+") | D49: =COUNTIFS($C$6:$C$45,$B49,$D$6:$D$45,"−") | E49: =COUNTIFS($C$6:$C$45,$B49,$D$6:$D$45,"−",$I$6:$I$45,"Open") | F49: =COUNTIFS($C$6:$C$45,$B49,$D$6:$D$45,"+",$G$6:$G$45,"No")
B50: Schedule | C50: =COUNTIFS($C$6:$C$45,$B50,$D$6:$D$45,"+") | D50: =COUNTIFS($C$6:$C$45,$B50,$D$6:$D$45,"−") | E50: =COUNTIFS($C$6:$C$45,$B50,$D$6:$D$45,"−",$I$6:$I$45,"Open") | F50: =COUNTIFS($C$6:$C$45,$B50,$D$6:$D$45,"+",$G$6:$G$45,"No")
B51: Cost Control | C51: =COUNTIFS($C$6:$C$45,$B51,$D$6:$D$45,"+") | D51: =COUNTIFS($C$6:$C$45,$B51,$D$6:$D$45,"−") | E51: =COUNTIFS($C$6:$C$45,$B51,$D$6:$D$45,"−",$I$6:$I$45,"Open") | F51: =COUNTIFS($C$6:$C$45,$B51,$D$6:$D$45,"+",$G$6:$G$45,"No")
B52: Management | C52: =COUNTIFS($C$6:$C$45,$B52,$D$6:$D$45,"+") | D52: =COUNTIFS($C$6:$C$45,$B52,$D$6:$D$45,"−") | E52: =COUNTIFS($C$6:$C$45,$B52,$D$6:$D$45,"−",$I$6:$I$45,"Open") | F52: =COUNTIFS($C$6:$C$45,$B52,$D$6:$D$45,"+",$G$6:$G$45,"No")
B53: Small Business Utilization | C53: =COUNTIFS($C$6:$C$45,$B53,$D$6:$D$45,"+") | D53: =COUNTIFS($C$6:$C$45,$B53,$D$6:$D$45,"−") | E53: =COUNTIFS($C$6:$C$45,$B53,$D$6:$D$45,"−",$I$6:$I$45,"Open") | F53: =COUNTIFS($C$6:$C$45,$B53,$D$6:$D$45,"+",$G$6:$G$45,"No")
B54: Regulatory Compliance | C54: =COUNTIFS($C$6:$C$45,$B54,$D$6:$D$45,"+") | D54: =COUNTIFS($C$6:$C$45,$B54,$D$6:$D$45,"−") | E54: =COUNTIFS($C$6:$C$45,$B54,$D$6:$D$45,"−",$I$6:$I$45,"Open") | F54: =COUNTIFS($C$6:$C$45,$B54,$D$6:$D$45,"+",$G$6:$G$45,"No")
B56: Yellow in "not yet shared" means you have evidence the COR has never seen. It does not count until they have it in writing. Red in "still open" means a negative that will be on the draft rating unless you close it.
B58: Acqlerate CPARS Playbook · acqlerate.com · September 2026 Edition

Sheet Self-Assessment
B2: Self-Assessment: Predict Your Rating Before the Draft Arrives
B3: Rate yourself honestly against the Rating Decoder. Evidence counts come from the log. If your self-rating is higher than your evidence supports, the AO will not give it to you either.
B5: Area | C5: My rating | D5: Positive evidence | E5: Negative open | F5: Not shared | G5: Target rating | H5: What justifies my rating (cite log rows) | I5: Gap to target: action before period end
B6: Quality | C6: Satisfactory | D6: ='Evidence Log'!C49 | E6: ='Evidence Log'!E49 | F6: ='Evidence Log'!F49 | G6: Very Good
B7: Schedule | C7: Satisfactory | D7: ='Evidence Log'!C50 | E7: ='Evidence Log'!E50 | F7: ='Evidence Log'!F50 | G7: Very Good
B8: Cost Control | C8: Satisfactory | D8: ='Evidence Log'!C51 | E8: ='Evidence Log'!E51 | F8: ='Evidence Log'!F51 | G8: Very Good
B9: Management | C9: Satisfactory | D9: ='Evidence Log'!C52 | E9: ='Evidence Log'!E52 | F9: ='Evidence Log'!F52 | G9: Very Good
B10: Small Business Utilization | C10: Satisfactory | D10: ='Evidence Log'!C53 | E10: ='Evidence Log'!E53 | F10: ='Evidence Log'!F53 | G10: Very Good
B11: Regulatory Compliance | C11: Satisfactory | D11: ='Evidence Log'!C54 | E11: ='Evidence Log'!E54 | F11: ='Evidence Log'!F54 | G11: Very Good
B13: REALITY CHECK
B14: Area | C14: Evidence supports | D14: My rating | E14: Flag
B15: Quality | C15: =IF(E6>0,"Marginal or below",IF(D6-F6>=4,"Exceptional",IF(D6-F6>=2,"Very Good","Satisfactory"))) | D15: =C6 | E15: =IF(E6>0,"OPEN NEGATIVE: close it",IF(MATCH(C6,{"Unsatisfactory","Marginal","Satisfactory","Very Good","Exceptional"},0)>MATCH(C15,{"Marginal or below","Satisfactory","Very Good","Exceptional"},0)+1,"Rating exceeds evidence","Supported"))
B16: Schedule | C16: =IF(E7>0,"Marginal or below",IF(D7-F7>=4,"Exceptional",IF(D7-F7>=2,"Very Good","Satisfactory"))) | D16: =C7 | E16: =IF(E7>0,"OPEN NEGATIVE: close it",IF(MATCH(C7,{"Unsatisfactory","Marginal","Satisfactory","Very Good","Exceptional"},0)>MATCH(C16,{"Marginal or below","Satisfactory","Very Good","Exceptional"},0)+1,"Rating exceeds evidence","Supported"))
B17: Cost Control | C17: =IF(E8>0,"Marginal or below",IF(D8-F8>=4,"Exceptional",IF(D8-F8>=2,"Very Good","Satisfactory"))) | D17: =C8 | E17: =IF(E8>0,"OPEN NEGATIVE: close it",IF(MATCH(C8,{"Unsatisfactory","Marginal","Satisfactory","Very Good","Exceptional"},0)>MATCH(C17,{"Marginal or below","Satisfactory","Very Good","Exceptional"},0)+1,"Rating exceeds evidence","Supported"))
B18: Management | C18: =IF(E9>0,"Marginal or below",IF(D9-F9>=4,"Exceptional",IF(D9-F9>=2,"Very Good","Satisfactory"))) | D18: =C9 | E18: =IF(E9>0,"OPEN NEGATIVE: close it",IF(MATCH(C9,{"Unsatisfactory","Marginal","Satisfactory","Very Good","Exceptional"},0)>MATCH(C18,{"Marginal or below","Satisfactory","Very Good","Exceptional"},0)+1,"Rating exceeds evidence","Supported"))
B19: Small Business Utilization | C19: =IF(E10>0,"Marginal or below",IF(D10-F10>=4,"Exceptional",IF(D10-F10>=2,"Very Good","Satisfactory"))) | D19: =C10 | E19: =IF(E10>0,"OPEN NEGATIVE: close it",IF(MATCH(C10,{"Unsatisfactory","Marginal","Satisfactory","Very Good","Exceptional"},0)>MATCH(C19,{"Marginal or below","Satisfactory","Very Good","Exceptional"},0)+1,"Rating exceeds evidence","Supported"))
B20: Regulatory Compliance | C20: =IF(E11>0,"Marginal or below",IF(D11-F11>=4,"Exceptional",IF(D11-F11>=2,"Very Good","Satisfactory"))) | D20: =C11 | E20: =IF(E11>0,"OPEN NEGATIVE: close it",IF(MATCH(C11,{"Unsatisfactory","Marginal","Satisfactory","Very Good","Exceptional"},0)>MATCH(C20,{"Marginal or below","Satisfactory","Very Good","Exceptional"},0)+1,"Rating exceeds evidence","Supported"))
B22: Rule of thumb built into the check: Very Good needs at least two shared positive events in the area; Exceptional needs four or more; any open negative caps you at Marginal until it is closed. Adjust to your COR, but do not expect a rating your log cannot support.
B24: Acqlerate CPARS Playbook · acqlerate.com · September 2026 Edition

Sheet Interim Check-In
B2: Interim Check-In: No Surprises at the Final Rating
B3: Schedule this with your COR at the mid-point of every rating period. Ask these questions, write down the answers, and act on them. A rating you first hear about in the draft is a rating you have already lost.
B5: Area | C5: Ask the COR | D5: What the answer tells you | E5: Their answer (date) | F5: Action taken
B6: Quality | C6: If you were rating quality today, what would it be, and what one thing would move it up? | D6: If they cannot name the thing that would move it up, they have not seen your evidence. Send it.
B7: Schedule | C7: Is there any milestone you consider late or at risk from your side? | D7: Their view of "late" may differ from yours. Reconcile now, not in the comment period.
B8: Cost Control | C8: Is our cost reporting giving you what you need, on time? Any concerns on burn rate? | D8: Cost Control is the area most often rated Satisfactory by default. Ask what Very Good would look like.
B9: Management | C9: Any communication or responsiveness issues from your side? Anything you had to escalate? | D9: If they escalated anything, it is on the draft. Find out what and close it.
B10: Small Business Utilization | C10: Have you seen the latest ISR/SSR? Any concerns about goals? | D10: Late or inaccurate reports are the most common cause of a Marginal here. Confirm they have them.
B11: Regulatory Compliance | C11: Any compliance concern on your side we should know about? CMMC, safety, export, security? | D11: Compliance findings are often known to the Government before the contractor. Ask.
B12: Overall | C12: Is there anything that, if it continued, would result in a rating below Satisfactory? | D12: This is the question that prevents a surprise Marginal. Ask it directly.
B13: Overall | C13: What would it take for you to rate us Exceptional in any area? | D13: Now you know what to document for the rest of the period.
B15: Timing: mid-point of the rating period at minimum; quarterly on a cost-type contract. Bring the Evidence Log tally. Leave with a written record of what they said.
B17: Acqlerate CPARS Playbook · acqlerate.com · September 2026 Edition

Sheet Rebuttal Builder
B2: Rebuttal Builder: The 14-Day Response
B3: Only for a draft rating you can prove is wrong against the contract. Build the argument here, then write the comment. Fourteen calendar days from notification (FAR 42.1503); if still unresolved, you may request review one level above the Contracting Officer.
B4: Draft notification date: | C4: 46280
B5: Area | C5: Rating given / sought | D5: The specific contractual requirement (cite clause, CDRL, PWS paragraph) | E5: Evidence that we met or exceeded it (log rows, dates, documents) | F5: Proposed comment language | G5: Days remaining
B6: Quality | C6: Satisfactory → Very Good | D6: Example: PWS 3.2.1 requires acceptance test defect density below 2 per KSLOC. Increment 2 delivered at 0.4 per KSLOC (Test Report TR-2026-07). | E6: Example: Evidence Log rows 7/28 and 7/14. Government acceptance signed same day; no rework cycle. | F6: Example: "We respectfully request the Quality rating be revised to Very Good. PWS 3.2.1 sets a defect density threshold of 2.0/KSLOC; Increment 2 was accepted at 0.4/KSLOC (TR-2026-07), with acceptance signed the day of delivery and no rework. We believe this exceeds the requirement to the Government’s benefit." | G6: =IF($C$4="","",MAX(0,14-(TODAY()-$C$4)))
B7: Schedule | G7: =IF($C$4="","",MAX(0,14-(TODAY()-$C$4)))
B8: Cost Control | G8: =IF($C$4="","",MAX(0,14-(TODAY()-$C$4)))
B9: Management | G9: =IF($C$4="","",MAX(0,14-(TODAY()-$C$4)))
B10: Small Business Utilization | G10: =IF($C$4="","",MAX(0,14-(TODAY()-$C$4)))
B11: Regulatory Compliance | G11: =IF($C$4="","",MAX(0,14-(TODAY()-$C$4)))
B13: WHAT TO ARGUE
B14: The contract said X. We did X or better. Here is the document that proves it. That is the entire argument.
B15: Argue against the rating, area by area. Do not argue against the Assessing Official.
B16: Cite the PWS paragraph, the CDRL, the clause. A rebuttal without a citation is an opinion.
B17: Attach or reference the evidence by document number and date. Make it easy to verify.
B19: WHAT NOT TO ARGUE
B20: Effort. "We worked very hard" is not a contractual requirement.
B21: Government-caused delays, unless you have a documented request for equitable adjustment or a letter from the period. Raising it for the first time in the rebuttal reads as an excuse.
B22: Tone. Every sentence of your comment stays in the system for three years and is read by future source selection boards. Write for them.
B23: Everything. A rebuttal on six areas dilutes the one you can win. Pick the areas where the contract and the evidence are unambiguous.
B25: IF THE CO DOES NOT REVISE
B26: Request review by the official one level above the Contracting Officer (FAR 42.1503(d)). State the request in your comment. Your comments remain attached to the record either way, so write them as if the rebuttal is the last word, because it may be.
B28: Acqlerate CPARS Playbook · acqlerate.com · September 2026 Edition
