Workbook

Sheet Start Here
B2: PM Essentials — Your First 90 Days as a DoD Program Manager
B3: One workbook. Fill in the tabs, and the Dashboard builds your program status for you.
B5: How this workbook fits together
B6: 1. Dashboard — reads every other tab and gives you a one-page program status. Print it for your PEO. You fill in only the header (program, PM, as-of date).
B7: 2. First 90 Days — the 30 things to do when you inherit a program, in order. Mark them off; the Dashboard tracks your progress.
B8: 3. Spend Plan — monthly obligation and expenditure plan vs. actuals for the fiscal year, against your appropriation’s obligation goal. This is the tab you will live in.
B9: 4. Risk Register — 16 pre-loaded risks that actually kill DoD programs, scored and with mitigations. Rescore them for your program; the Risk Map redraws itself.
B10: 5. Risk Map — your risks plotted on the 5×5 grid. Print this page for the weekly review.
B11: 6. RACI — 25 program decisions with who is Responsible, Accountable, Consulted, Informed. One row per decision, four fields, no grid to maintain.
B12: 7. PM Briefing Deck (separate PowerPoint) — 12 slides with the questions leadership will actually ask, in the speaker notes.
B14: Where each tool is taught
B15: Spend Plan and color of money → Module 2: Defense Finance & Budgeting, Lesson 1 and Lesson 8
... B25: Licensed for use on one program, by one organization. Customize text, branding, and layout freely. Company-wide deployment, sharing outside your organization, or resale requires an Acqlerate Team License (acqlerate.com/team).

Sheet Dashboard
B2: PROGRAM DASHBOARD
B3: Builds itself from the other tabs. Fill in the three header cells, then print this page for your PEO.
B5: Program | C5: [Program Name]
B6: Program Manager | C6: [Your Name]
B7: As of | C7: 46280
B9: MONEY | E9: RISK | H9: HOW TO READ THIS
B10: Appropriation | C10: ='Spend Plan'!C6 | E10: HIGH | F10: =COUNTIF('Risk Register'!I16:I31,"HIGH") | H10: MONEY goes red when cumulative obligations fall more than 10% behind plan. If the appropriation expires this FY, that is the slide to lead with.
B11: Budget Authority | C11: ='Spend Plan'!C7 | E11: MEDIUM | F11: =COUNTIF('Risk Register'!I16:I31,"MEDIUM")
B12: Obligated to date | C12: ='Spend Plan'!C29 | E12: LOW | F12: =COUNTIF('Risk Register'!I16:I31,"LOW")
B13: % of BA obligated | C13: ='Spend Plan'!C30 | E13: Open | F13: =COUNTIF('Risk Register'!N16:N31,"Open") | H13: RISK is red at three or more HIGH risks. The list shows every open HIGH — each one needs a mitigation owner named on the register.
B14: % of plan achieved | C14: ='Spend Plan'!C31 | E14: Status | F14: =IF(F10>=3,"RED",IF(F10>=1,"AMBER","GREEN"))
B15: Remaining to Yr-1 goal | C15: ='Spend Plan'!C32 | E15: HIGH risks (open)
B16: Status | C16: ='Spend Plan'!C34 | E16: {=_xlfn.TEXTJOIN(CHAR(10),TRUE,IF(('Risk Register'!$I$16:$I$31="HIGH")*('Risk Register'!$N$16:$N$31="Open"),'Risk Register'!$B$16:$B$31&" "&'Risk Register'!$C$16:$C$31,""))} | H16: FIRST 90 DAYS shows where you are in taking over the program. Below 50% on Orient after day 30 means you are still finding out things you should already know.
H19: ACCOUNTABILITY is red if any decision in the RACI has no Accountable owner. That is the gap that turns into “I thought you had that.”
B21: FIRST 90 DAYS | E21: ACCOUNTABILITY
B22: Orient (1–30) | C22: ='First 90 Days'!F39 | E22: Decisions tracked | F22: =COUNTA('RACI'!B8:B32)
B23: Assess (31–60) | C23: ='First 90 Days'!F40 | E23: Missing an Accountable | F23: =COUNTBLANK('RACI'!D8:D32)
B24: Act (61–90) | C24: ='First 90 Days'!F41 | E24: Status | F24: =IF(F23=0,"GREEN","RED")
B25: Overall | C25: ='First 90 Days'!F42
B28: Acqlerate PM Essentials · acqlerate.com · September 2026 Edition · Reflects FAC 2025-06

Sheet First 90 Days
B2: First 90 Days — Inheriting a DoD Program
B3: Thirty things to do, in order. Mark Status as you go; the Dashboard tracks each phase.
B5: # | C5: Action | D5: Phase | E5: Status | F5: Owner | G5: Notes / Evidence
B6: 1 | C6: Read the Acquisition Program Baseline and Acquisition Strategy. Know your cost, schedule, and performance thresholds before anyone asks. | D6: Orient (Days 1–30) | E6: Not Started
B7: 2 | C7: Schedule 1:1s in week one with your PEO, Contracting Officer, COR, and the contractor PM. Ask each: what worries you most? | D7: Orient (Days 1–30) | E7: Not Started
B8: 3 | C8: Pull the last three PMR decks. Read the risk and cost slides first — that is where the truth lives. | D8: Orient (Days 1–30) | E8: Not Started
B9: 4 | C9: Find the current spend plan and obligation status. Know your color of money and when each appropriation expires. | D9: Orient (Days 1–30) | E9: Not Started
B10: 5 | C10: Get read-in on every active contract: type, period of performance, CLIN structure, remaining options, ceiling. | D10: Orient (Days 1–30) | E10: Not Started
B11: 6 | C11: Review the contractor’s last two CPARS and every open CAR or deficiency report. | D11: Orient (Days 1–30) | E11: Not Started
B12: 7 | C12: Confirm the RACI (RACI tab): who is Accountable for each decision. Fix the blanks now, not in a crisis. | D12: Orient (Days 1–30) | E12: Not Started
B13: 8 | C13: List every milestone, decision, and test event inside the next 90 days. These are your forcing functions. | D13: Orient (Days 1–30) | E13: Not Started
B14: 9 | C14: Verify CMMC on every contract handling FCI or CUI: the required level, and a current status posted in SPRS for the contractor and each covered sub. Phase 2 C3PAO assessments are suspended (July 2026); check for a new date before you plan around one. | D14: Orient (Days 1–30) | E14: Not Started
B15: 10 | C15: Stand up the Risk Register (Risk Register tab) with the outgoing PM’s top ten. Do not rescore yet — just capture. | D15: Orient (Days 1–30) | E15: Not Started
B16: 11 | C16: Rescore every risk with your own probability and impact. Brief the Risk Map to your PEO within the phase. | D16: Assess (Days 31–60) | E16: Not Started
B17: 12 | C17: Reconcile obligations against plan (Spend Plan tab). Flag any appropriation at risk of expiring unobligated. | D17: Assess (Days 31–60) | E17: Not Started
... B35: 30 | C35: Schedule the six-month look-ahead review and put the date on the Dashboard. | D35: Act (Days 61–90) | E35: Not Started
B37: PROGRESS
C38: Phase | D38: Done | E38: Total | F38: % Complete
C39: Orient (Days 1–30) | D39: =COUNTIF(E6:E15,"Done") | E39: =COUNTA(E6:E15)-COUNTIF(E6:E15,"N/A") | F39: =IF(E39=0,0,D39/E39)
C40: Assess (Days 31–60) | D40: =COUNTIF(E16:E25,"Done") | E40: =COUNTA(E16:E25)-COUNTIF(E16:E25,"N/A") | F40: =IF(E40=0,0,D40/E40)
C41: Act (Days 61–90) | D41: =COUNTIF(E26:E35,"Done") | E41: =COUNTA(E26:E35)-COUNTIF(E26:E35,"N/A") | F41: =IF(E41=0,0,D41/E41)
C42: OVERALL | D42: =SUM(D39:D41) | E42: =SUM(E39:E41) | F42: =IF(E42=0,0,D42/E42)
B44: Acqlerate PM Essentials · acqlerate.com · September 2026 Edition · Reflects FAC 2025-06

Sheet Spend Plan
B2: Spend Plan — Obligations & Expenditures vs. Plan
B3: One fiscal year, one appropriation line. Enter the plan, then post actuals each month. Status and the Dashboard update themselves.
I4: Appropriation | J4: Yrs Available | K4: Yr-1 Oblig Goal
B5: Fiscal Year | C5: FY2027 | I5: O&M | J5: 1 | K5: 1
B6: Appropriation | C6: O&M | I6: RDT&E | J6: 2 | K6: 0.9
B7: Total Budget Authority | C7: 4150000 | I7: Procurement | J7: 3 | K7: 0.8
B8: Years Available | C8: =VLOOKUP(C6,$I$5:$K$8,2,FALSE) | I8: Typical OSD first-year obligation goals. Verify against your Component’s current guidance — they change.
B9: Obligation Goal (Yr 1) | C9: =VLOOKUP(C6,$I$5:$K$8,3,FALSE)
B10: Goal $ (Yr 1) | C10: =C7*C9
B12: Month | C12: Planned Oblig | D12: Actual Oblig | E12: Cum Planned | F12: Cum Actual | G12: Variance $ | H12: Variance % | I12: Status | J12: Planned Exp | K12: Actual Exp | L12: Cum Plan Exp | M12: Cum Act Exp
B13: Oct | C13: 249000 | D13: 207500 | E13: =C13+0 | F13: =IF(D13="","",D13+N(0)) | G13: =IF(F13="","",F13-E13) | H13: =IF(F13="","",IF(E13=0,0,(F13-E13)/E13)) | I13: =IF(F13="","",IF(H13<-0.1,"BEHIND",IF(H13>0.1,"AHEAD","ON PLAN"))) | J13: 83000 | K13: 83000 | L13: =J13+0 | M13: =IF(K13="","",K13+N(0))
B14: Nov | C14: 332000 | D14: 290500 | E14: =C14+E13 | F14: =IF(D14="","",D14+N(F13)) | G14: =IF(F14="","",F14-E14) | H14: =IF(F14="","",IF(E14=0,0,(F14-E14)/E14)) | I14: =IF(F14="","",IF(H14<-0.1,"BEHIND",IF(H14>0.1,"AHEAD","ON PLAN"))) | J14: 166000 | K14: 124500 | L14: =J14+L13 | M14: =IF(K14="","",K14+N(M13))
B15: Dec | C15: 415000 | D15: 456500 | E15: =C15+E14 | F15: =IF(D15="","",D15+N(F14)) | G15: =IF(F15="","",F15-E15) | H15: =IF(F15="","",IF(E15=0,0,(F15-E15)/E15)) | I15: =IF(F15="","",IF(H15<-0.1,"BEHIND",IF(H15>0.1,"AHEAD","ON PLAN"))) | J15: 249000 | K15: 207500 | L15: =J15+L14 | M15: =IF(K15="","",K15+N(M14))
B16: Jan | C16: 373500 | D16: 332000 | E16: =C16+E15 | F16: =IF(D16="","",D16+N(F15)) | G16: =IF(F16="","",F16-E16) | H16: =IF(F16="","",IF(E16=0,0,(F16-E16)/E16)) | I16: =IF(F16="","",IF(H16<-0.1,"BEHIND",IF(H16>0.1,"AHEAD","ON PLAN"))) | J16: 332000 | K16: 290500 | L16: =J16+L15 | M16: =IF(K16="","",K16+N(M15))
B17: Feb | C17: 373500 | D17: 415000 | E17: =C17+E16 | F17: =IF(D17="","",D17+N(F16)) | G17: =IF(F17="","",F17-E17) | H17: =IF(F17="","",IF(E17=0,0,(F17-E17)/E17)) | I17: =IF(F17="","",IF(H17<-0.1,"BEHIND",IF(H17>0.1,"AHEAD","ON PLAN"))) | J17: 373500 | K17: 373500 | L17: =J17+L16 | M17: =IF(K17="","",K17+N(M16))
B18: Mar | C18: 373500 | D18: 332000 | E18: =C18+E17 | F18: =IF(D18="","",D18+N(F17)) | G18: =IF(F18="","",F18-E18) | H18: =IF(F18="","",IF(E18=0,0,(F18-E18)/E18)) | I18: =IF(F18="","",IF(H18<-0.1,"BEHIND",IF(H18>0.1,"AHEAD","ON PLAN"))) | J18: 415000 | K18: 373500 | L18: =J18+L17 | M18: =IF(K18="","",K18+N(M17))
B19: Apr | C19: 373500 | E19: =C19+E18 | F19: =IF(D19="","",D19+N(F18)) | G19: =IF(F19="","",F19-E19) | H19: =IF(F19="","",IF(E19=0,0,(F19-E19)/E19)) | I19: =IF(F19="","",IF(H19<-0.1,"BEHIND",IF(H19>0.1,"AHEAD","ON PLAN"))) | J19: 415000 | L19: =J19+L18 | M19: =IF(K19="","",K19+N(M18))
B20: May | C20: 373500 | E20: =C20+E19 | F20: =IF(D20="","",D20+N(F19)) | G20: =IF(F20="","",F20-E20) | H20: =IF(F20="","",IF(E20=0,0,(F20-E20)/E20)) | I20: =IF(F20="","",IF(H20<-0.1,"BEHIND",IF(H20>0.1,"AHEAD","ON PLAN"))) | J20: 415000 | L20: =J20+L19 | M20: =IF(K20="","",K20+N(M19))
B21: Jun | C21: 373500 | E21: =C21+E20 | F21: =IF(D21="","",D21+N(F20)) | G21: =IF(F21="","",F21-E21) | H21: =IF(F21="","",IF(E21=0,0,(F21-E21)/E21)) | I21: =IF(F21="","",IF(H21<-0.1,"BEHIND",IF(H21>0.1,"AHEAD","ON PLAN"))) | J21: 415000 | L21: =J21+L20 | M21: =IF(K21="","",K21+N(M20))
B22: Jul | C22: 332000 | E22: =C22+E21 | F22: =IF(D22="","",D22+N(F21)) | G22: =IF(F22="","",F22-E22) | H22: =IF(F22="","",IF(E22=0,0,(F22-E22)/E22)) | I22: =IF(F22="","",IF(H22<-0.1,"BEHIND",IF(H22>0.1,"AHEAD","ON PLAN"))) | J22: 415000 | L22: =J22+L21 | M22: =IF(K22="","",K22+N(M21))
B23: Aug | C23: 290500 | E23: =C23+E22 | F23: =IF(D23="","",D23+N(F22)) | G23: =IF(F23="","",F23-E23) | H23: =IF(F23="","",IF(E23=0,0,(F23-E23)/E23)) | I23: =IF(F23="","",IF(H23<-0.1,"BEHIND",IF(H23>0.1,"AHEAD","ON PLAN"))) | J23: 456500 | L23: =J23+L22 | M23: =IF(K23="","",K23+N(M22))
B24: Sep | C24: 290500 | E24: =C24+E23 | F24: =IF(D24="","",D24+N(F23)) | G24: =IF(F24="","",F24-E24) | H24: =IF(F24="","",IF(E24=0,0,(F24-E24)/E24)) | I24: =IF(F24="","",IF(H24<-0.1,"BEHIND",IF(H24>0.1,"AHEAD","ON PLAN"))) | J24: 415000 | L24: =J24+L23 | M24: =IF(K24="","",K24+N(M23))
B26: YEAR-TO-DATE
B27: Months posted | C27: =COUNT(D13:D24)
B28: Planned to date | C28: =IF(C27=0,0,INDEX(E13:E24,C27))
B29: Obligated to date | C29: =IF(C27=0,0,INDEX(F13:F24,C27))
B30: % of BA obligated | C30: =IF(C7=0,0,C29/C7)
B31: % of plan achieved | C31: =IF(C28=0,0,C29/C28)
B32: Remaining to Yr-1 goal | C32: =MAX(0,C10-C29)
B33: Expended to date | C33: =IF(C27=0,0,INDEX(M13:M24,C27))
B34: Overall status | C34: =IF(C27=0,"No actuals posted",IF(C31<0.9,"BEHIND PLAN",IF(C31>1.1,"AHEAD OF PLAN","ON PLAN")))
B36: BEHIND / AHEAD trip at ±10% of cumulative plan. An expiring appropriation that is BEHIND in Q3 is the number-one avoidable failure in program finance — act in Q2.
B38: Acqlerate PM Essentials · acqlerate.com · September 2026 Edition · Reflects FAC 2025-06

Sheet Risk Register
B2: DoD Program Risk Register
B3: Track, assess, and mitigate program risks per DoD Risk Management Framework
B5: Risk Summary
B6: By Risk Level | E6: By Category | H6: By Status
B7: HIGH | C7: =COUNTIF(I16:I31,"HIGH") | E7: Technical | F7: =COUNTIF(D16:D31,"Technical") | H7: Open | I7: =COUNTIF(N16:N31,"Open")
B8: MEDIUM | C8: =COUNTIF(I16:I31,"MEDIUM") | E8: Schedule | F8: =COUNTIF(D16:D31,"Schedule") | H8: Mitigated | I8: =COUNTIF(N16:N31,"Mitigated")
B9: LOW | C9: =COUNTIF(I16:I31,"LOW") | E9: Cost | F9: =COUNTIF(D16:D31,"Cost") | H9: Closed | I9: =COUNTIF(N16:N31,"Closed")
E10: External | F10: =COUNTIF(D16:D31,"External") | H10: Accepted | I10: =COUNTIF(N16:N31,"Accepted")
E11: Programmatic | F11: =COUNTIF(D16:D31,"Programmatic")
B13: Risk Register
B14: Change Probability and Impact (1–5) for your program. Score, Level, the Risk Map, and the Dashboard update themselves.
B15: ID | C15: Risk | D15: Category | E15: Description | F15: Probability (1–5) | G15: Impact (1–5) | H15: Score (P×I) | I15: Level | J15: Mitigation | K15: Contingency | L15: Owner | M15: Target Date | N15: Status | O15: Date Identified
B16: R-001 | C16: Software Integration Failure | D16: Technical | E16: Integration of legacy C4ISR systems with new cloud-based architecture may fail due to incompatible interfaces and undocumented APIs | F16: 4 | G16: 5 | H16: =F16*G16 | I16: =IF(H16>=15,"HIGH",IF(H16>=8,"MEDIUM","LOW")) | J16: Conduct early integration testing in sprint 2; establish interface control documents (ICDs) before CDR | K16: Revert to point-to-point integration with middleware adapter layer | L16: Systems Engineer | M16: 46134 | N16: Open | O16: 46104
B17: R-002 | C17: Key Personnel Departure | D17: Programmatic | E17: Program Manager or Technical Lead may depart during performance period, causing knowledge loss and schedule delays | F17: 3 | G17: 4 | H17: =F17*G17 | I17: =IF(H17>=15,"HIGH",IF(H17>=8,"MEDIUM","LOW")) | J17: Cross-train deputy PM; maintain knowledge repository; include retention incentives in compensation plan | K17: Activate pre-identified replacement from bench; execute 30-day transition plan | L17: HR Director | M17: 46164 | N17: Open | O17: 46104
B18: R-003 | C18: Requirements Creep | D18: Schedule | E18: Government may issue numerous contract modifications expanding scope without proportional schedule/cost adjustments | F18: 4 | G18: 4 | H18: =F18*G18 | I18: =IF(H18>=15,"HIGH",IF(H18>=8,"MEDIUM","LOW")) | J18: Establish formal change control board; track all requirements changes against baseline; negotiate equitable adjustments promptly | K18: Invoke REA process; request stop-work on unfunded requirements until modification is executed | L18: PM | M18: 46149 | N18: Open | O18: 46104
B19: R-004 | C19: Funding Shortfall / CR Impact | D19: Cost | E19: Continuing Resolution or sequestration may reduce available program funding below planned obligation levels | F19: 3 | G19: 5 | H19: =F19*G19 | I19: =IF(H19>=15,"HIGH",IF(H19>=8,"MEDIUM","LOW")) | J19: Maintain prioritized requirements backlog; identify minimum viable capability set; coordinate with PEO on funding alternatives | K19: Descope optional CLINs; defer non-critical deliverables to subsequent option years | L19: Finance Director | M19: 46194 | N19: Open | O19: 46104
B20: R-005 | C20: Subcontractor Performance | D20: External | E20: Critical subcontractor (cybersecurity toolset provider) may fail to deliver on schedule or meet quality standards | F20: 3 | G20: 4 | H20: =F20*G20 | I20: =IF(H20>=15,"HIGH",IF(H20>=8,"MEDIUM","LOW")) | J20: Conduct monthly sub performance reviews; include liquidated damages clause; maintain qualified alternate vendor list | K20: Activate alternate vendor under pre-negotiated teaming agreement; absorb initial ramp-up costs | L20: Subcontracts Mgr | M20: 46134 | N20: Open | O20: 46104
B21: R-006 | C21: CMMC Requirements Change | D21: External | E21: CMMC Phase 1 (self-assessments) has been in contracts since Nov 10, 2025. Phase 2 (C3PAO certification for Level 2) was suspended July 13, 2026 pending a DoD reform review, with no new date. The program is exposed if third-party assessments return mid-contract, or if a contractor's SPRS self-assessment does not hold up. | F21: 2 | G21: 5 | H21: =F21*G21 | I21: =IF(H21>=15,"HIGH",IF(H21>=8,"MEDIUM","LOW")) | J21: Confirm each contract's required CMMC level and that current status is posted in SPRS; close any POA&M items inside the 180-day window. Track the reform review and the next DFARS change. Keep a C3PAO readiness plan on the shelf, not on the schedule. | K21: If a new Phase 2 date lands inside the period of performance, brief the CO on schedule and cost impact and price assessments into the next option or mod. Make sure SPRS scores reflect current NIST SP 800-171 implementation. | L21: ISSM | M21: 46224 | N21: Mitigated | O21: 46104
B22: R-007 | C22: Test Environment Unavailability | D22: Technical | E22: Government-furnished test range or lab environment may not be available during scheduled test windows | F22: 3 | G22: 3 | H22: =F22*G22 | I22: =IF(H22>=15,"HIGH",IF(H22>=8,"MEDIUM","LOW")) | J22: Reserve test windows 90 days in advance; develop simulation environment for initial testing; coordinate with range scheduling office | K22: Use contractor lab environment with government-approved test procedures; reschedule to next available window | L22: Test Director | M22: 46149 | N22: Open | O22: 46104
B23: R-008 | C23: Data Rights Dispute | D23: Programmatic | E23: Disagreement with government over technical data rights (DFARS 252.227-7013) may delay deliverable acceptance | F23: 2 | G23: 4 | H23: =F23*G23 | I23: =IF(H23>=15,"HIGH",IF(H23>=8,"MEDIUM","LOW")) | J23: Document all data rights assertions in proposal; maintain IP development records; engage legal counsel early | K23: Negotiate limited rights license; escalate to CO for determination; consider ASBCA claim if unresolved | L23: Legal Counsel | M23: 46164 | N23: Accepted | O23: 46104
B24: R-009 | C24: EVM Compliance Gaps | D24: Cost | E24: Earned Value Management System may not meet ANSI/EIA-748 standards, resulting in DCMA surveillance findings | F24: 2 | G24: 3 | H24: =F24*G24 | I24: =IF(H24>=15,"HIGH",IF(H24>=8,"MEDIUM","LOW")) | J24: Conduct EVMS self-assessment; train all CAMs on EVM procedures; schedule pre-IBR dry run | K24: Engage EVM consultant for remediation; request corrective action timeline extension from DCMA | L24: Finance Director | M24: 46134 | N24: Mitigated | O24: 46104
B25: R-010 | C25: Supply Chain Disruption | D25: External | E25: Critical hardware components (FPGA chips, ruggedized servers) may face extended lead times exceeding 6 months | F25: 4 | G25: 3 | H25: =F25*G25 | I25: =IF(H25>=15,"HIGH",IF(H25>=8,"MEDIUM","LOW")) | J25: Order long-lead items at contract award; qualify multiple vendors; maintain safety stock for critical components | K25: Redesign with available commercial alternatives; negotiate schedule relief through REA | L25: Logistics Mgr | M25: 46119 | N25: Open | O25: 46104
B26: R-011 | C26: Clearance Processing Delays | D26: Schedule | E26: Personnel security clearance investigations may exceed expected timelines, delaying staffing of classified positions | F26: 3 | G26: 3 | H26: =F26*G26 | I26: =IF(H26>=15,"HIGH",IF(H26>=8,"MEDIUM","LOW")) | J26: Submit clearance requests immediately upon contract award; utilize interim clearances where permissible; pre-identify cleared alternates | K26: Assign cleared personnel from other programs temporarily; adjust task sequencing to prioritize unclassified work | L26: FSO | M26: 46134 | N26: Open | O26: 46104
B27: R-012 | C27: Technical Debt Accumulation | D27: Technical | E27: Aggressive delivery schedule may force shortcuts in code quality, increasing defect rates and long-term maintenance costs | F27: 3 | G27: 3 | H27: =F27*G27 | I27: =IF(H27>=15,"HIGH",IF(H27>=8,"MEDIUM","LOW")) | J27: Allocate 20% sprint capacity for refactoring; enforce code review gates; track technical debt backlog | K27: Dedicate full sprint to debt reduction when defect rate exceeds threshold; engage additional developers | L27: Tech Lead | M27: 46164 | N27: Open | O27: 46104
... B31: R-016 | C31: CMMC Level 2 Non-Compliance | D31: External | E31: Subcontractors handling FCI or CUI may not have a current CMMC status in SPRS at the required level. The prime must flow down DFARS 252.204-7021 and confirm sub status before award; a sub that falls out of status puts CUI-handling work at risk. | F31: 3 | G31: 5 | H31: =F31*G31 | I31: =IF(H31>=15,"HIGH",IF(H31>=8,"MEDIUM","LOW")) | J31: Confirm current CMMC status in SPRS for every subcontractor handling FCI or CUI; get POA&M closeout dates in writing; budget for a C3PAO assessment in case the Phase 2 suspension ends. | K31: Pre-qualify an alternate subcontractor with a current CMMC status at the required level; be ready to transition CUI-handling work on short notice. | L31: Subcontracts Mgr | M31: 46296 | N31: Open | O31: 46266
B34: Template by Acqlerate — Defense Acquisitions Academy | www.acqlerate.com

Sheet Risk Map
B2: 5×5 Probability / Impact Risk Matrix
B3: Risk Score = Probability × Impact | GREEN ≤7 (LOW) | YELLOW 8-14 (MEDIUM) | RED ≥15 (HIGH)
B5: Probability ↓ / Impact → | C5: 1 — Negligible | D5: 2 — Minor | E5: 3 — Moderate | F5: 4 — Significant | G5: 5 — Critical
B6: 5 — Almost Certain | C6: 5 | D6: 10 | E6: 15 | F6: 20 | G6: 25
B7: 4 — Likely | C7: 4 | D7: 8 | E7: 12 | F7: 16 | G7: 20
B8: 3 — Possible | C8: 3 | D8: 6 | E8: 9 | F8: 12 | G8: 15
B9: 2 — Unlikely | C9: 2 | D9: 4 | E9: 6 | F9: 8 | G9: 10
B10: 1 — Rare | C10: 1 | D10: 2 | E10: 3 | F10: 4 | G10: 5
B13: Legend
B14: HIGH (≥15) | C14: Unacceptable risk — requires immediate mitigation action and leadership attention
B15: MEDIUM (8-14) | C15: Elevated risk — requires active monitoring and mitigation planning
B16: LOW (≤7) | C16: Acceptable risk — monitor periodically; no immediate action required
B19: Template by Acqlerate — Defense Acquisitions Academy | www.acqlerate.com
B22: Where Your Risks Land
B23: Pulls live from the Risk Register. Print this page and drop it straight into your weekly program review slide.
B25: Probability ↓ / Impact → | C25: 1 — Negligible | D25: 2 — Minor | E25: 3 — Moderate | F25: 4 — Significant | G25: 5 — Critical
B26: 5 — Almost Certain | C26: {=_xlfn.TEXTJOIN(", ",TRUE,IF(('Risk Register'!$F$16:$F$31=5)*('Risk Register'!$G$16:$G$31=1),'Risk Register'!$B$16:$B$31,""))} | D26: {=_xlfn.TEXTJOIN(", ",TRUE,IF(('Risk Register'!$F$16:$F$31=5)*('Risk Register'!$G$16:$G$31=2),'Risk Register'!$B$16:$B$31,""))} | E26: {=_xlfn.TEXTJOIN(", ",TRUE,IF(('Risk Register'!$F$16:$F$31=5)*('Risk Register'!$G$16:$G$31=3),'Risk Register'!$B$16:$B$31,""))} | F26: {=_xlfn.TEXTJOIN(", ",TRUE,IF(('Risk Register'!$F$16:$F$31=5)*('Risk Register'!$G$16:$G$31=4),'Risk Register'!$B$16:$B$31,""))} | G26: {=_xlfn.TEXTJOIN(", ",TRUE,IF(('Risk Register'!$F$16:$F$31=5)*('Risk Register'!$G$16:$G$31=5),'Risk Register'!$B$16:$B$31,""))}
B27: 4 — Likely | C27: {=_xlfn.TEXTJOIN(", ",TRUE,IF(('Risk Register'!$F$16:$F$31=4)*('Risk Register'!$G$16:$G$31=1),'Risk Register'!$B$16:$B$31,""))} | D27: {=_xlfn.TEXTJOIN(", ",TRUE,IF(('Risk Register'!$F$16:$F$31=4)*('Risk Register'!$G$16:$G$31=2),'Risk Register'!$B$16:$B$31,""))} | E27: {=_xlfn.TEXTJOIN(", ",TRUE,IF(('Risk Register'!$F$16:$F$31=4)*('Risk Register'!$G$16:$G$31=3),'Risk Register'!$B$16:$B$31,""))} | F27: {=_xlfn.TEXTJOIN(", ",TRUE,IF(('Risk Register'!$F$16:$F$31=4)*('Risk Register'!$G$16:$G$31=4),'Risk Register'!$B$16:$B$31,""))} | G27: {=_xlfn.TEXTJOIN(", ",TRUE,IF(('Risk Register'!$F$16:$F$31=4)*('Risk Register'!$G$16:$G$31=5),'Risk Register'!$B$16:$B$31,""))}
B28: 3 — Possible | C28: {=_xlfn.TEXTJOIN(", ",TRUE,IF(('Risk Register'!$F$16:$F$31=3)*('Risk Register'!$G$16:$G$31=1),'Risk Register'!$B$16:$B$31,""))} | D28: {=_xlfn.TEXTJOIN(", ",TRUE,IF(('Risk Register'!$F$16:$F$31=3)*('Risk Register'!$G$16:$G$31=2),'Risk Register'!$B$16:$B$31,""))} | E28: {=_xlfn.TEXTJOIN(", ",TRUE,IF(('Risk Register'!$F$16:$F$31=3)*('Risk Register'!$G$16:$G$31=3),'Risk Register'!$B$16:$B$31,""))} | F28: {=_xlfn.TEXTJOIN(", ",TRUE,IF(('Risk Register'!$F$16:$F$31=3)*('Risk Register'!$G$16:$G$31=4),'Risk Register'!$B$16:$B$31,""))} | G28: {=_xlfn.TEXTJOIN(", ",TRUE,IF(('Risk Register'!$F$16:$F$31=3)*('Risk Register'!$G$16:$G$31=5),'Risk Register'!$B$16:$B$31,""))}
B29: 2 — Unlikely | C29: {=_xlfn.TEXTJOIN(", ",TRUE,IF(('Risk Register'!$F$16:$F$31=2)*('Risk Register'!$G$16:$G$31=1),'Risk Register'!$B$16:$B$31,""))} | D29: {=_xlfn.TEXTJOIN(", ",TRUE,IF(('Risk Register'!$F$16:$F$31=2)*('Risk Register'!$G$16:$G$31=2),'Risk Register'!$B$16:$B$31,""))} | E29: {=_xlfn.TEXTJOIN(", ",TRUE,IF(('Risk Register'!$F$16:$F$31=2)*('Risk Register'!$G$16:$G$31=3),'Risk Register'!$B$16:$B$31,""))} | F29: {=_xlfn.TEXTJOIN(", ",TRUE,IF(('Risk Register'!$F$16:$F$31=2)*('Risk Register'!$G$16:$G$31=4),'Risk Register'!$B$16:$B$31,""))} | G29: {=_xlfn.TEXTJOIN(", ",TRUE,IF(('Risk Register'!$F$16:$F$31=2)*('Risk Register'!$G$16:$G$31=5),'Risk Register'!$B$16:$B$31,""))}
B30: 1 — Rare | C30: {=_xlfn.TEXTJOIN(", ",TRUE,IF(('Risk Register'!$F$16:$F$31=1)*('Risk Register'!$G$16:$G$31=1),'Risk Register'!$B$16:$B$31,""))} | D30: {=_xlfn.TEXTJOIN(", ",TRUE,IF(('Risk Register'!$F$16:$F$31=1)*('Risk Register'!$G$16:$G$31=2),'Risk Register'!$B$16:$B$31,""))} | E30: {=_xlfn.TEXTJOIN(", ",TRUE,IF(('Risk Register'!$F$16:$F$31=1)*('Risk Register'!$G$16:$G$31=3),'Risk Register'!$B$16:$B$31,""))} | F30: {=_xlfn.TEXTJOIN(", ",TRUE,IF(('Risk Register'!$F$16:$F$31=1)*('Risk Register'!$G$16:$G$31=4),'Risk Register'!$B$16:$B$31,""))} | G30: {=_xlfn.TEXTJOIN(", ",TRUE,IF(('Risk Register'!$F$16:$F$31=1)*('Risk Register'!$G$16:$G$31=5),'Risk Register'!$B$16:$B$31,""))}
B33: Blank cell = no risk currently scored at that Probability × Impact combination.
B35: License & Use
B36: This template is licensed for use on one program, by one organization, under your Acqlerate purchase. Customize the text, branding, and layout freely for your own program. Deploying it company-wide, sharing it outside your organization, or reselling it requires an Acqlerate Team License (acqlerate.com/team).

Sheet RACI
B2: RACI Matrix — DoD Program Stakeholders (Simplified)
B3: One row per activity. List the Responsible and Accountable role, plus anyone to Consult or Inform.
B5: Legend: R = Responsible (does the work) | A = Accountable (owns the outcome, one per row)
B6: C = Consulted (input before the decision) | I = Informed (notified after)
B7: Activity / Decision | C7: Responsible (R) | D7: Accountable (A) | E7: Consulted (C) | F7: Informed (I)
B8: Program Initiation | C8: PM | D8: PEO | E8: CO, Systems Engineer, Finance, Legal | F8: COR, DCMA, Contractor PM
B9: Requirements Development | C9: PM, Systems Engineer | D9: PEO | E9: COR, Contractor PM | F9: CO, DCMA, Finance, Legal
B10: Acquisition Strategy | C10: PM | D10: PEO | E10: CO, DCAA, Systems Engineer, Finance, Legal | F10: COR, DCMA, Contractor PM
B11: Source Selection Planning | C11: CO | D11: PEO | E11: PM, COR, Systems Engineer, Legal | F11: DCMA, Contractor PM, Finance
B12: RFP Development & Release | C12: CO | D12: PEO | E12: PM, COR, Systems Engineer, Legal | F12: Finance
B13: Proposal Evaluation | C13: PM, Systems Engineer | D13: CO | E13: COR, Finance, Legal | F13: PEO
B14: Contract Award | C14: CO | D14: PEO | E14: Finance, Legal | F14: PM, COR, DCMA, Contractor PM
B15: Kickoff Meeting | C15: PM, COR, Contractor PM | D15: PM | E15: CO, Systems Engineer | F15: PEO, DCMA, Finance
B16: Monthly IPR / Status Review | C16: PM, Contractor PM | D16: COR | E16: Systems Engineer, Finance | F16: PEO, CO, DCMA
B17: Quarterly Program Review | C17: PM, Contractor PM | D17: PEO | E17: COR, DCMA, Systems Engineer, Finance | F17: CO
B18: EVM / CPR Review | C18: PM, Contractor PM, Finance | D18: PM | E18: COR, DCMA, DCAA | F18: PEO, CO
... B32: Lessons Learned / AAR | C32: PM, Contractor PM | D32: PM | E32: COR, Systems Engineer | F32: PEO, CO, DCMA, Finance
B34: Template by Acqlerate — Defense Acquisitions Academy | www.acqlerate.com
B35: Generated: September 2026 | Updated: FAC 2025-06

Sheet RACI Instructions
B2: RACI Matrix — Instructions
B4: Purpose
B5: The RACI matrix clarifies who does the work, who owns the outcome, who gets consulted, and who just needs to know. It prevents the "I thought you were handling that" problem on DoD programs.
B7: Why this version is a list, not a grid
B8: The classic RACI matrix (one column per stakeholder role) is thorough but nobody keeps it updated: adding a new activity means filling in ten columns. This version flips it: one row per activity, with just four fields. Adding or editing an activity takes seconds.
B10: RACI Definitions
B11: R — Responsible: The person or role that performs the work. More than one person can be Responsible.
B12: A — Accountable: The single person with final authority for the outcome. Exactly one per activity, no exceptions.
B13: C — Consulted: People whose input is sought before the decision or action (two-way conversation).
B14: I — Informed: People notified after the decision or action (one-way notice).
B16: Stakeholder Roles Used in This Template
B17: PM: Government Program Manager — overall program execution authority, accountable to the PEO for cost, schedule, and performance.
... B39: This template is licensed for use on one program, by one organization, under your Acqlerate purchase. Customize the text, branding, and layout freely for your own program. Deploying it company-wide, sharing it outside your organization, or reselling it requires an Acqlerate Team License (acqlerate.com/team).
