Workbook

Sheet Instructions
B1: Acqlerate
B2: DoD Acquisition Training · acqlerate.com
A4: Cost & Burn Rate Tracker — How to Use This
A6: What this is:
A7: A working cost model for a contractor PM: enter your negotiated rates once, log labor, ODCs, and
A8: travel as they happen, and the Dashboard tab builds up your fully burdened cost, applies G&A and fee,
A9: and tracks it against your funded ceiling month by month — the same buildup your finance team runs,
A10: just visible to you instead of buried in a system you don't have access to.
A12: Tab order — fill these in first, in this order:
A13: 1. Rates — your negotiated Fringe, Overhead, G&A, and Fee rates. Everything else depends on these.
A14: 2. FundingMods — log your original award and every funding modification since. This is what sets
A15: your current TOA (Total Obligated Amount) — it is NOT a single static number anymore, it's the
A16: running total of your funding log, which is how it actually works on a real contract.
A17: 3. Dashboard — enter Program Name, Contract #, and Period of Performance dates near the top.
... A64: company's DCAA-approved rate structure — the defaults here are common conventions, not universal ones.

Sheet Rates
B1: Negotiated Rates | C1: Acqlerate · acqlerate.com
A3: Fringe Rate (%) | B3: 0.35 | C3: Applied to Direct Labor. Covers benefits (health, retirement, PTO).
A4: Overhead (OH) Rate (%) | B4: 0.55 | C4: Applied to (Direct Labor + Fringe). Covers indirect labor, facilities, and fringe on indirect staff. Base varies by company — check your DCAA-approved rate agreement.
A5: G&A Rate (%) | B5: 0.12 | C5: Applied to Total Cost Input (fully burdened labor + ODCs + Travel). Covers company-wide G&A: executive, finance, HR, business development.
A7: Fee Type in Use | B7: Fixed | C7: Type exactly "Fixed" or "Award" (case-sensitive) to switch which fee rate below is used.
A8: Fixed Fee Rate (%) | B8: 0.07 | C8: Used if Fee Type = "Fixed". A flat % of Total Cost that doesn't vary with performance (CPFF).
A9: Target Award Fee Rate (%) | B9: 0.1 | C9: Used if Fee Type = "Award". This is the MAX pool rate — actual earned fee depends on your award fee score (see the CPAF lesson). This tracker assumes 100% earned for planning; adjust down if you have a current-period score.
A11: Applicable Fee Rate (auto) | B11: =IF(B7="Fixed",B8,IF(B7="Award",B9,NA())) -> 0.07 | C11: Picked automatically from the Fee Type cell above. This is what the Dashboard tab actually uses.
A13: Fee base note: | C13: This tracker applies fee to Total Cost (burdened labor + ODCs + Travel + G&A). Some contracts exclude ODCs, travel, or facilities capital cost of money from the fee base — check your specific contract's fee clause (FAR 52.216 series) before relying on this for real billing.

Sheet FundingMods
B1: Funding Modification Log | E1: Acqlerate · acqlerate.com
A3: Mod # | B3: Date | C3: Description | D3: Funding Added / (Removed) $ | E3: Cumulative TOA $
A4: P00000 (Award) | B4: 46023 | C4: Original award — base period | D4: 2000000 | E4: =IF(D4="","",D4) -> 2000000
A5: P00001 | B5: 46143 | C5: Incremental funding — added scope | D5: 400000 | E5: =IF(D5="","",SUM($D$4:D5)) -> 2400000
E6: =IF(D6="","",SUM($D$4:D6))
E7: =IF(D7="","",SUM($D$4:D7))
E8: =IF(D8="","",SUM($D$4:D8))
E9: =IF(D9="","",SUM($D$4:D9))
E10: =IF(D10="","",SUM($D$4:D10))
E11: =IF(D11="","",SUM($D$4:D11))
E12: =IF(D12="","",SUM($D$4:D12))
E13: =IF(D13="","",SUM($D$4:D13))
A15: Current TOA (auto) | B15: =IFERROR(INDEX(E4:E13,COUNT(D4:D13)),0) -> 2400000 | C15: The cumulative total as of the last modification entered above.
A17: Acqlerate · DoD Acquisition Training · acqlerate.com

Sheet Dashboard
B1: Cost & Burn Rate Dashboard | O1: Acqlerate · acqlerate.com
A3: Program / Contract Name | C3: Example: Fleet Sustainment Support Services
A4: Contract / Task Order # | C4: N00019-25-F-0142
A5: Period of Performance — Start | C5: 46023
A6: Period of Performance — End | C6: 46387
A7: Months in Period | C7: =DATEDIF(C5,C6,"m")+1 -> 12
A8: Current TOA (from FundingMods tab) | C8: =FundingMods!$B$15 -> 2400000
A9: Straight-Line Monthly Plan | C9: =C8/C7 -> 200000
A11: SUMMARY
A12: Months of Actuals Entered | C12: =COUNT(D21:D32) -> 12
A13: Spent to Date | C13: =IF(C12=0,0,INDEX(L21:L32,C12)) -> 158475.58
A14: Remaining Funds | C14: =C8-C13 -> 2241524.4
A15: % of TOA Spent | C15: =IFERROR(C13/C8,0) -> 0.06603149
A16: Current Monthly Burn Rate (3-mo avg) | C16: =IFERROR(AVERAGE(OFFSET(K21,MAX(C12-3,0),0,MIN(C12,3),1)),0) -> 0
A17: Projected Months to Exhaustion | C17: =IFERROR(C14/C16,"—") -> —
A18: Status | C18: =IF(C12=0,"NO DATA YET",IF(C15>(C12/C7)*1.1,"AT RISK — OVERRUNNING",IF(C15<(C12/C7)*0.7,"AT RISK — UNDERRUNNING (option year risk)","ON TRACK"))) -> AT RISK — UNDERRUNNING (option year risk)
A20: Month # | B20: Month | C20: Planned Cumulative $ | D20: Labor $ | E20: ODCs $ | F20: Travel $ | G20: Subtotal (L+O+T) | H20: G&A $ | I20: Total Cost | J20: Fee $ | K20: Total Billed (This Month) | L20: Actual Cumulative $ | M20: Variance $ | N20: Variance % | O20: Remaining Funds $
A21: 1 | B21: =EDATE($C$5,A21-1) -> 46023 | C21: =$C$9*A21 -> 200000 | D21: =Labor!C129 -> 40118.144 | E21: =IF(D21="","",ODCs!C27) -> 14200 | F21: =IF(D21="","",Travel!C27) -> 1090 | G21: =IF(D21="","",D21+E21+F21) -> 55408.144 | H21: =IF(G21="","",G21*Rates!$B$5) -> 6648.9773 | I21: =IF(G21="","",G21+H21) -> 62057.122 | J21: =IF(I21="","",I21*Rates!$B$11) -> 4343.9985 | K21: =IF(I21="","",I21+J21) -> 66401.12 | L21: =IF(SUM($K$21:K21)=0,"",SUM($K$21:K21)) -> 66401.12 | M21: =IF(OR(L21="",C21=""),"",L21-C21) -> -133598.88 | N21: =IF(OR(L21="",C21="",C21=0),"",M21/C21) -> -0.6679944 | O21: =IF(L21="","",$C$8-L21) -> 2333598.9
A22: 2 | B22: =EDATE($C$5,A22-1) -> 46054 | C22: =$C$9*A22 -> 400000 | D22: =Labor!C130 -> 28771.322 | E22: =IF(D22="","",ODCs!C28) -> 3100 | F22: =IF(D22="","",Travel!C28) -> 0 | G22: =IF(D22="","",D22+E22+F22) -> 31871.322 | H22: =IF(G22="","",G22*Rates!$B$5) -> 3824.5586 | I22: =IF(G22="","",G22+H22) -> 35695.88 | J22: =IF(I22="","",I22*Rates!$B$11) -> 2498.7116 | K22: =IF(I22="","",I22+J22) -> 38194.592 | L22: =IF(SUM($K$21:K22)=0,"",SUM($K$21:K22)) -> 104595.71 | M22: =IF(OR(L22="",C22=""),"",L22-C22) -> -295404.29 | N22: =IF(OR(L22="",C22="",C22=0),"",M22/C22) -> -0.73851072 | O22: =IF(L22="","",$C$8-L22) -> 2295404.3
A23: 3 | B23: =EDATE($C$5,A23-1) -> 46082 | C23: =$C$9*A23 -> 600000 | D23: =Labor!C131 -> 0 | E23: =IF(D23="","",ODCs!C29) -> 0 | F23: =IF(D23="","",Travel!C29) -> 1150 | G23: =IF(D23="","",D23+E23+F23) -> 1150 | H23: =IF(G23="","",G23*Rates!$B$5) -> 138 | I23: =IF(G23="","",G23+H23) -> 1288 | J23: =IF(I23="","",I23*Rates!$B$11) -> 90.16 | K23: =IF(I23="","",I23+J23) -> 1378.16 | L23: =IF(SUM($K$21:K23)=0,"",SUM($K$21:K23)) -> 105973.87 | M23: =IF(OR(L23="",C23=""),"",L23-C23) -> -494026.13 | N23: =IF(OR(L23="",C23="",C23=0),"",M23/C23) -> -0.82337688 | O23: =IF(L23="","",$C$8-L23) -> 2294026.1
A24: 4 | B24: =EDATE($C$5,A24-1) -> 46113 | C24: =$C$9*A24 -> 800000 | D24: =Labor!C132 -> 0 | E24: =IF(D24="","",ODCs!C30) -> 8600 | F24: =IF(D24="","",Travel!C30) -> 0 | G24: =IF(D24="","",D24+E24+F24) -> 8600 | H24: =IF(G24="","",G24*Rates!$B$5) -> 1032 | I24: =IF(G24="","",G24+H24) -> 9632 | J24: =IF(I24="","",I24*Rates!$B$11) -> 674.24 | K24: =IF(I24="","",I24+J24) -> 10306.24 | L24: =IF(SUM($K$21:K24)=0,"",SUM($K$21:K24)) -> 116280.11 | M24: =IF(OR(L24="",C24=""),"",L24-C24) -> -683719.89 | N24: =IF(OR(L24="",C24="",C24=0),"",M24/C24) -> -0.85464986 | O24: =IF(L24="","",$C$8-L24) -> 2283719.9
A25: 5 | B25: =EDATE($C$5,A25-1) -> 46143 | C25: =$C$9*A25 -> 1000000 | D25: =Labor!C133 -> 0 | E25: =IF(D25="","",ODCs!C31) -> 0 | F25: =IF(D25="","",Travel!C31) -> 0 | G25: =IF(D25="","",D25+E25+F25) -> 0 | H25: =IF(G25="","",G25*Rates!$B$5) -> 0 | I25: =IF(G25="","",G25+H25) -> 0 | J25: =IF(I25="","",I25*Rates!$B$11) -> 0 | K25: =IF(I25="","",I25+J25) -> 0 | L25: =IF(SUM($K$21:K25)=0,"",SUM($K$21:K25)) -> 116280.11 | M25: =IF(OR(L25="",C25=""),"",L25-C25) -> -883719.89 | N25: =IF(OR(L25="",C25="",C25=0),"",M25/C25) -> -0.88371989 | O25: =IF(L25="","",$C$8-L25) -> 2283719.9
A26: 6 | B26: =EDATE($C$5,A26-1) -> 46174 | C26: =$C$9*A26 -> 1200000 | D26: =Labor!C134 -> 0 | E26: =IF(D26="","",ODCs!C32) -> 0 | F26: =IF(D26="","",Travel!C32) -> 0 | G26: =IF(D26="","",D26+E26+F26) -> 0 | H26: =IF(G26="","",G26*Rates!$B$5) -> 0 | I26: =IF(G26="","",G26+H26) -> 0 | J26: =IF(I26="","",I26*Rates!$B$11) -> 0 | K26: =IF(I26="","",I26+J26) -> 0 | L26: =IF(SUM($K$21:K26)=0,"",SUM($K$21:K26)) -> 116280.11 | M26: =IF(OR(L26="",C26=""),"",L26-C26) -> -1083719.9 | N26: =IF(OR(L26="",C26="",C26=0),"",M26/C26) -> -0.90309991 | O26: =IF(L26="","",$C$8-L26) -> 2283719.9
A27: 7 | B27: =EDATE($C$5,A27-1) -> 46204 | C27: =$C$9*A27 -> 1400000 | D27: =Labor!C135 -> 9054.0865 | E27: =IF(D27="","",ODCs!C33) -> 0 | F27: =IF(D27="","",Travel!C33) -> 0 | G27: =IF(D27="","",D27+E27+F27) -> 9054.0865 | H27: =IF(G27="","",G27*Rates!$B$5) -> 1086.4904 | I27: =IF(G27="","",G27+H27) -> 10140.577 | J27: =IF(I27="","",I27*Rates!$B$11) -> 709.84038 | K27: =IF(I27="","",I27+J27) -> 10850.417 | L27: =IF(SUM($K$21:K27)=0,"",SUM($K$21:K27)) -> 127130.53 | M27: =IF(OR(L27="",C27=""),"",L27-C27) -> -1272869.5 | N27: =IF(OR(L27="",C27="",C27=0),"",M27/C27) -> -0.90919248 | O27: =IF(L27="","",$C$8-L27) -> 2272869.5
A28: 8 | B28: =EDATE($C$5,A28-1) -> 46235 | C28: =$C$9*A28 -> 1600000 | D28: =Labor!C136 -> 26155.747 | E28: =IF(D28="","",ODCs!C34) -> 0 | F28: =IF(D28="","",Travel!C34) -> 0 | G28: =IF(D28="","",D28+E28+F28) -> 26155.747 | H28: =IF(G28="","",G28*Rates!$B$5) -> 3138.6896 | I28: =IF(G28="","",G28+H28) -> 29294.437 | J28: =IF(I28="","",I28*Rates!$B$11) -> 2050.6106 | K28: =IF(I28="","",I28+J28) -> 31345.047 | L28: =IF(SUM($K$21:K28)=0,"",SUM($K$21:K28)) -> 158475.58 | M28: =IF(OR(L28="",C28=""),"",L28-C28) -> -1441524.4 | N28: =IF(OR(L28="",C28="",C28=0),"",M28/C28) -> -0.90095276 | O28: =IF(L28="","",$C$8-L28) -> 2241524.4
A29: 9 | B29: =EDATE($C$5,A29-1) -> 46266 | C29: =$C$9*A29 -> 1800000 | D29: =Labor!C137 -> 0 | E29: =IF(D29="","",ODCs!C35) -> 0 | F29: =IF(D29="","",Travel!C35) -> 0 | G29: =IF(D29="","",D29+E29+F29) -> 0 | H29: =IF(G29="","",G29*Rates!$B$5) -> 0 | I29: =IF(G29="","",G29+H29) -> 0 | J29: =IF(I29="","",I29*Rates!$B$11) -> 0 | K29: =IF(I29="","",I29+J29) -> 0 | L29: =IF(SUM($K$21:K29)=0,"",SUM($K$21:K29)) -> 158475.58 | M29: =IF(OR(L29="",C29=""),"",L29-C29) -> -1641524.4 | N29: =IF(OR(L29="",C29="",C29=0),"",M29/C29) -> -0.91195801 | O29: =IF(L29="","",$C$8-L29) -> 2241524.4
A30: 10 | B30: =EDATE($C$5,A30-1) -> 46296 | C30: =$C$9*A30 -> 2000000 | D30: =Labor!C138 -> 0 | E30: =IF(D30="","",ODCs!C36) -> 0 | F30: =IF(D30="","",Travel!C36) -> 0 | G30: =IF(D30="","",D30+E30+F30) -> 0 | H30: =IF(G30="","",G30*Rates!$B$5) -> 0 | I30: =IF(G30="","",G30+H30) -> 0 | J30: =IF(I30="","",I30*Rates!$B$11) -> 0 | K30: =IF(I30="","",I30+J30) -> 0 | L30: =IF(SUM($K$21:K30)=0,"",SUM($K$21:K30)) -> 158475.58 | M30: =IF(OR(L30="",C30=""),"",L30-C30) -> -1841524.4 | N30: =IF(OR(L30="",C30="",C30=0),"",M30/C30) -> -0.92076221 | O30: =IF(L30="","",$C$8-L30) -> 2241524.4
A31: 11 | B31: =EDATE($C$5,A31-1) -> 46327 | C31: =$C$9*A31 -> 2200000 | D31: =Labor!C139 -> 0 | E31: =IF(D31="","",ODCs!C37) -> 0 | F31: =IF(D31="","",Travel!C37) -> 0 | G31: =IF(D31="","",D31+E31+F31) -> 0 | H31: =IF(G31="","",G31*Rates!$B$5) -> 0 | I31: =IF(G31="","",G31+H31) -> 0 | J31: =IF(I31="","",I31*Rates!$B$11) -> 0 | K31: =IF(I31="","",I31+J31) -> 0 | L31: =IF(SUM($K$21:K31)=0,"",SUM($K$21:K31)) -> 158475.58 | M31: =IF(OR(L31="",C31=""),"",L31-C31) -> -2041524.4 | N31: =IF(OR(L31="",C31="",C31=0),"",M31/C31) -> -0.92796565 | O31: =IF(L31="","",$C$8-L31) -> 2241524.4
A32: 12 | B32: =EDATE($C$5,A32-1) -> 46357 | C32: =$C$9*A32 -> 2400000 | D32: =Labor!C140 -> 0 | E32: =IF(D32="","",ODCs!C38) -> 0 | F32: =IF(D32="","",Travel!C38) -> 0 | G32: =IF(D32="","",D32+E32+F32) -> 0 | H32: =IF(G32="","",G32*Rates!$B$5) -> 0 | I32: =IF(G32="","",G32+H32) -> 0 | J32: =IF(I32="","",I32*Rates!$B$11) -> 0 | K32: =IF(I32="","",I32+J32) -> 0 | L32: =IF(SUM($K$21:K32)=0,"",SUM($K$21:K32)) -> 158475.58 | M32: =IF(OR(L32="",C32=""),"",L32-C32) -> -2241524.4 | N32: =IF(OR(L32="",C32="",C32=0),"",M32/C32) -> -0.93396851 | O32: =IF(L32="","",$C$8-L32) -> 2241524.4
A34: Acqlerate · DoD Acquisition Training · acqlerate.com

Sheet Personnel
B1: Personnel | Q1: Acqlerate · acqlerate.com
A3: One row per person. Enter Employee Type as exactly "Exempt" (salaried) or "Non-Exempt" (hourly, OT-eligible).
A4: Employee # | B4: Employee Name | C4: LCAT | D4: Employee Type | E4: Annual Salary (Exempt only) | F4: Direct Hourly Rate (Non-Exempt only) | G4: Standard Annual Hours | H4: Straight-Time Rate $/hr | I4: OT Rate $/hr (1.5x) | J4: Start Date | K4: End Date (optional) | L4: PTO Accrual (hrs/mo) | M4: PTO Beginning Balance (hrs) | N4: Months Worked YTD | O4: PTO Accrued YTD | P4: PTO Used YTD | Q4: PTO Balance (hrs)
A5: 123456 | B5: John Smith | C5: Engineer 4 | D5: Exempt | E5: 150000 | G5: 2080 | H5: =IF(A5="","",IF(D5="Exempt",IF(G5=0,"",E5/G5),F5)) -> 72.115385 | I5: =IF(A5="","",IF(D5="Non-Exempt",H5*1.5,"N/A")) -> N/A | J5: 46213 | L5: 8 | M5: 0 | N5: =IF(A5="","",COUNTIFS(Labor!$A$5:$A$124,A5,Labor!$F$5:$F$124,"<>")) -> 2 | O5: =IF(A5="","",L5*N5) -> 16 | P5: =IF(A5="","",SUMIFS(Labor!$H$5:$H$124,Labor!$A$5:$A$124,A5)) -> 0 | Q5: =IF(A5="","",M5+O5-P5) -> 16
A6: 123457 | B6: Maria Alvarez | C6: Program Manager | D6: Exempt | E6: 165000 | G6: 2080 | H6: =IF(A6="","",IF(D6="Exempt",IF(G6=0,"",E6/G6),F6)) -> 79.326923 | I6: =IF(A6="","",IF(D6="Non-Exempt",H6*1.5,"N/A")) -> N/A | J6: 46023 | L6: 8 | M6: 12 | N6: =IF(A6="","",COUNTIFS(Labor!$A$5:$A$124,A6,Labor!$F$5:$F$124,"<>")) -> 2 | O6: =IF(A6="","",L6*N6) -> 16 | P6: =IF(A6="","",SUMIFS(Labor!$H$5:$H$124,Labor!$A$5:$A$124,A6)) -> 8 | Q6: =IF(A6="","",M6+O6-P6) -> 20
A7: 123458 | B7: Dave Chen | C7: Admin Support | D7: Non-Exempt | F7: 28.5 | G7: 2080 | H7: =IF(A7="","",IF(D7="Exempt",IF(G7=0,"",E7/G7),F7)) -> 28.5 | I7: =IF(A7="","",IF(D7="Non-Exempt",H7*1.5,"N/A")) -> 42.75 | J7: 46023 | L7: 6.67 | M7: 5 | N7: =IF(A7="","",COUNTIFS(Labor!$A$5:$A$124,A7,Labor!$F$5:$F$124,"<>")) -> 1 | O7: =IF(A7="","",L7*N7) -> 6.67 | P7: =IF(A7="","",SUMIFS(Labor!$H$5:$H$124,Labor!$A$5:$A$124,A7)) -> 0 | Q7: =IF(A7="","",M7+O7-P7) -> 11.67
G8: 2080 | H8: =IF(A8="","",IF(D8="Exempt",IF(G8=0,"",E8/G8),F8)) | I8: =IF(A8="","",IF(D8="Non-Exempt",H8*1.5,"N/A")) | N8: =IF(A8="","",COUNTIFS(Labor!$A$5:$A$124,A8,Labor!$F$5:$F$124,"<>")) | O8: =IF(A8="","",L8*N8) | P8: =IF(A8="","",SUMIFS(Labor!$H$5:$H$124,Labor!$A$5:$A$124,A8)) | Q8: =IF(A8="","",M8+O8-P8)
G9: 2080 | H9: =IF(A9="","",IF(D9="Exempt",IF(G9=0,"",E9/G9),F9)) | I9: =IF(A9="","",IF(D9="Non-Exempt",H9*1.5,"N/A")) | N9: =IF(A9="","",COUNTIFS(Labor!$A$5:$A$124,A9,Labor!$F$5:$F$124,"<>")) | O9: =IF(A9="","",L9*N9) | P9: =IF(A9="","",SUMIFS(Labor!$H$5:$H$124,Labor!$A$5:$A$124,A9)) | Q9: =IF(A9="","",M9+O9-P9)
G10: 2080 | H10: =IF(A10="","",IF(D10="Exempt",IF(G10=0,"",E10/G10),F10)) | I10: =IF(A10="","",IF(D10="Non-Exempt",H10*1.5,"N/A")) | N10: =IF(A10="","",COUNTIFS(Labor!$A$5:$A$124,A10,Labor!$F$5:$F$124,"<>")) | O10: =IF(A10="","",L10*N10) | P10: =IF(A10="","",SUMIFS(Labor!$H$5:$H$124,Labor!$A$5:$A$124,A10)) | Q10: =IF(A10="","",M10+O10-P10)
G11: 2080 | H11: =IF(A11="","",IF(D11="Exempt",IF(G11=0,"",E11/G11),F11)) | I11: =IF(A11="","",IF(D11="Non-Exempt",H11*1.5,"N/A")) | N11: =IF(A11="","",COUNTIFS(Labor!$A$5:$A$124,A11,Labor!$F$5:$F$124,"<>")) | O11: =IF(A11="","",L11*N11) | P11: =IF(A11="","",SUMIFS(Labor!$H$5:$H$124,Labor!$A$5:$A$124,A11)) | Q11: =IF(A11="","",M11+O11-P11)
G12: 2080 | H12: =IF(A12="","",IF(D12="Exempt",IF(G12=0,"",E12/G12),F12)) | I12: =IF(A12="","",IF(D12="Non-Exempt",H12*1.5,"N/A")) | N12: =IF(A12="","",COUNTIFS(Labor!$A$5:$A$124,A12,Labor!$F$5:$F$124,"<>")) | O12: =IF(A12="","",L12*N12) | P12: =IF(A12="","",SUMIFS(Labor!$H$5:$H$124,Labor!$A$5:$A$124,A12)) | Q12: =IF(A12="","",M12+O12-P12)
G13: 2080 | H13: =IF(A13="","",IF(D13="Exempt",IF(G13=0,"",E13/G13),F13)) | I13: =IF(A13="","",IF(D13="Non-Exempt",H13*1.5,"N/A")) | N13: =IF(A13="","",COUNTIFS(Labor!$A$5:$A$124,A13,Labor!$F$5:$F$124,"<>")) | O13: =IF(A13="","",L13*N13) | P13: =IF(A13="","",SUMIFS(Labor!$H$5:$H$124,Labor!$A$5:$A$124,A13)) | Q13: =IF(A13="","",M13+O13-P13)
G14: 2080 | H14: =IF(A14="","",IF(D14="Exempt",IF(G14=0,"",E14/G14),F14)) | I14: =IF(A14="","",IF(D14="Non-Exempt",H14*1.5,"N/A")) | N14: =IF(A14="","",COUNTIFS(Labor!$A$5:$A$124,A14,Labor!$F$5:$F$124,"<>")) | O14: =IF(A14="","",L14*N14) | P14: =IF(A14="","",SUMIFS(Labor!$H$5:$H$124,Labor!$A$5:$A$124,A14)) | Q14: =IF(A14="","",M14+O14-P14)
G15: 2080 | H15: =IF(A15="","",IF(D15="Exempt",IF(G15=0,"",E15/G15),F15)) | I15: =IF(A15="","",IF(D15="Non-Exempt",H15*1.5,"N/A")) | N15: =IF(A15="","",COUNTIFS(Labor!$A$5:$A$124,A15,Labor!$F$5:$F$124,"<>")) | O15: =IF(A15="","",L15*N15) | P15: =IF(A15="","",SUMIFS(Labor!$H$5:$H$124,Labor!$A$5:$A$124,A15)) | Q15: =IF(A15="","",M15+O15-P15)
G16: 2080 | H16: =IF(A16="","",IF(D16="Exempt",IF(G16=0,"",E16/G16),F16)) | I16: =IF(A16="","",IF(D16="Non-Exempt",H16*1.5,"N/A")) | N16: =IF(A16="","",COUNTIFS(Labor!$A$5:$A$124,A16,Labor!$F$5:$F$124,"<>")) | O16: =IF(A16="","",L16*N16) | P16: =IF(A16="","",SUMIFS(Labor!$H$5:$H$124,Labor!$A$5:$A$124,A16)) | Q16: =IF(A16="","",M16+O16-P16)
G17: 2080 | H17: =IF(A17="","",IF(D17="Exempt",IF(G17=0,"",E17/G17),F17)) | I17: =IF(A17="","",IF(D17="Non-Exempt",H17*1.5,"N/A")) | N17: =IF(A17="","",COUNTIFS(Labor!$A$5:$A$124,A17,Labor!$F$5:$F$124,"<>")) | O17: =IF(A17="","",L17*N17) | P17: =IF(A17="","",SUMIFS(Labor!$H$5:$H$124,Labor!$A$5:$A$124,A17)) | Q17: =IF(A17="","",M17+O17-P17)
G18: 2080 | H18: =IF(A18="","",IF(D18="Exempt",IF(G18=0,"",E18/G18),F18)) | I18: =IF(A18="","",IF(D18="Non-Exempt",H18*1.5,"N/A")) | N18: =IF(A18="","",COUNTIFS(Labor!$A$5:$A$124,A18,Labor!$F$5:$F$124,"<>")) | O18: =IF(A18="","",L18*N18) | P18: =IF(A18="","",SUMIFS(Labor!$H$5:$H$124,Labor!$A$5:$A$124,A18)) | Q18: =IF(A18="","",M18+O18-P18)
G19: 2080 | H19: =IF(A19="","",IF(D19="Exempt",IF(G19=0,"",E19/G19),F19)) | I19: =IF(A19="","",IF(D19="Non-Exempt",H19*1.5,"N/A")) | N19: =IF(A19="","",COUNTIFS(Labor!$A$5:$A$124,A19,Labor!$F$5:$F$124,"<>")) | O19: =IF(A19="","",L19*N19) | P19: =IF(A19="","",SUMIFS(Labor!$H$5:$H$124,Labor!$A$5:$A$124,A19)) | Q19: =IF(A19="","",M19+O19-P19)
A21: Acqlerate · DoD Acquisition Training · acqlerate.com

Sheet Labor
B1: Labor | S1: Acqlerate · acqlerate.com
A3: Itemized Timesheet Log — one row per person, per month worked
A4: Employee # | B4: Employee Name | C4: LCAT | D4: Month # | E4: Month | F4: Regular Hours | G4: OT Hours | H4: PTO Hours | I4: Permissible Hours | J4: Hours Variance | K4: Straight Rate $/hr | L4: OT Rate $/hr | M4: Regular $ | N4: OT $ | O4: PTO $ | P4: Direct Labor $ | Q4: Fringe $ | R4: OH $ | S4: Fully Burdened Labor $
A5: 123456 | B5: =IF(A5="","",IFERROR(INDEX(Personnel!$B$5:$B$19,MATCH($A5,Personnel!$A$5:$A$19,0)),"-- not found --")) -> John Smith | C5: =IF(A5="","",IFERROR(INDEX(Personnel!$C$5:$C$19,MATCH($A5,Personnel!$A$5:$A$19,0)),"")) -> Engineer 4 | D5: 7 | E5: =IF(D5="","",EDATE(Dashboard!$C$5,D5-1)) -> 46204 | F5: 60 | G5: 0 | H5: 0 | I5: =IFERROR(IF(OR(A5="",D5=""),"",MAX(0,(INDEX(Personnel!$G$5:$G$19,MATCH($A5,Personnel!$A$5:$A$19,0))/12)*((MIN(EOMONTH(E5,0),IF(INDEX(Personnel!$K$5:$K$19,MATCH($A5,Personnel!$A$5:$A$19,0))="",EOMONTH(E5,0),INDEX(Personnel!$K$5:$K$19,MATCH($A5,Personnel!$A$5:$A$19,0))))-MAX(DATE(YEAR(E5),MONTH(E5),1),INDEX(Personnel!$J$5:$J$19,MATCH($A5,Personnel!$A$5:$A$19,0)))+1)/DAY(EOMONTH(E5,0))))),"") -> 123.01075 | J5: =IF(OR(I5="",A5=""),"",(F5+G5+H5)-I5) -> -63.010753 | K5: =IF(A5="","",IFERROR(INDEX(Personnel!$H$5:$H$19,MATCH($A5,Personnel!$A$5:$A$19,0)),"")) -> 72.115385 | L5: =IF(A5="","",IFERROR(INDEX(Personnel!$I$5:$I$19,MATCH($A5,Personnel!$A$5:$A$19,0)),"")) -> N/A | M5: =IF(A5="","",F5*K5) -> 4326.9231 | N5: =IF(A5="","",IFERROR(G5*L5,0)) -> 0 | O5: =IF(A5="","",H5*K5) -> 0 | P5: =IF(A5="","",SUM(M5:O5)) -> 4326.9231 | Q5: =IF(P5="","",P5*Rates!$B$3) -> 1514.4231 | R5: =IF(P5="","",(P5+Q5)*Rates!$B$4) -> 3212.7404 | S5: =IF(P5="","",P5+Q5+R5) -> 9054.0865
A6: 123456 | B6: =IF(A6="","",IFERROR(INDEX(Personnel!$B$5:$B$19,MATCH($A6,Personnel!$A$5:$A$19,0)),"-- not found --")) -> John Smith | C6: =IF(A6="","",IFERROR(INDEX(Personnel!$C$5:$C$19,MATCH($A6,Personnel!$A$5:$A$19,0)),"")) -> Engineer 4 | D6: 8 | E6: =IF(D6="","",EDATE(Dashboard!$C$5,D6-1)) -> 46235 | F6: 173.33 | G6: 0 | H6: 0 | I6: =IFERROR(IF(OR(A6="",D6=""),"",MAX(0,(INDEX(Personnel!$G$5:$G$19,MATCH($A6,Personnel!$A$5:$A$19,0))/12)*((MIN(EOMONTH(E6,0),IF(INDEX(Personnel!$K$5:$K$19,MATCH($A6,Personnel!$A$5:$A$19,0))="",EOMONTH(E6,0),INDEX(Personnel!$K$5:$K$19,MATCH($A6,Personnel!$A$5:$A$19,0))))-MAX(DATE(YEAR(E6),MONTH(E6),1),INDEX(Personnel!$J$5:$J$19,MATCH($A6,Personnel!$A$5:$A$19,0)))+1)/DAY(EOMONTH(E6,0))))),"") -> 173.33333 | J6: =IF(OR(I6="",A6=""),"",(F6+G6+H6)-I6) -> -0.0033333333 | K6: =IF(A6="","",IFERROR(INDEX(Personnel!$H$5:$H$19,MATCH($A6,Personnel!$A$5:$A$19,0)),"")) -> 72.115385 | L6: =IF(A6="","",IFERROR(INDEX(Personnel!$I$5:$I$19,MATCH($A6,Personnel!$A$5:$A$19,0)),"")) -> N/A | M6: =IF(A6="","",F6*K6) -> 12499.76 | N6: =IF(A6="","",IFERROR(G6*L6,0)) -> 0 | O6: =IF(A6="","",H6*K6) -> 0 | P6: =IF(A6="","",SUM(M6:O6)) -> 12499.76 | Q6: =IF(P6="","",P6*Rates!$B$3) -> 4374.9159 | R6: =IF(P6="","",(P6+Q6)*Rates!$B$4) -> 9281.0715 | S6: =IF(P6="","",P6+Q6+R6) -> 26155.747
A7: 123457 | B7: =IF(A7="","",IFERROR(INDEX(Personnel!$B$5:$B$19,MATCH($A7,Personnel!$A$5:$A$19,0)),"-- not found --")) -> Maria Alvarez | C7: =IF(A7="","",IFERROR(INDEX(Personnel!$C$5:$C$19,MATCH($A7,Personnel!$A$5:$A$19,0)),"")) -> Program Manager | D7: 1 | E7: =IF(D7="","",EDATE(Dashboard!$C$5,D7-1)) -> 46023 | F7: 173.33 | G7: 0 | H7: 8 | I7: =IFERROR(IF(OR(A7="",D7=""),"",MAX(0,(INDEX(Personnel!$G$5:$G$19,MATCH($A7,Personnel!$A$5:$A$19,0))/12)*((MIN(EOMONTH(E7,0),IF(INDEX(Personnel!$K$5:$K$19,MATCH($A7,Personnel!$A$5:$A$19,0))="",EOMONTH(E7,0),INDEX(Personnel!$K$5:$K$19,MATCH($A7,Personnel!$A$5:$A$19,0))))-MAX(DATE(YEAR(E7),MONTH(E7),1),INDEX(Personnel!$J$5:$J$19,MATCH($A7,Personnel!$A$5:$A$19,0)))+1)/DAY(EOMONTH(E7,0))))),"") -> 173.33333 | J7: =IF(OR(I7="",A7=""),"",(F7+G7+H7)-I7) -> 7.9966667 | K7: =IF(A7="","",IFERROR(INDEX(Personnel!$H$5:$H$19,MATCH($A7,Personnel!$A$5:$A$19,0)),"")) -> 79.326923 | L7: =IF(A7="","",IFERROR(INDEX(Personnel!$I$5:$I$19,MATCH($A7,Personnel!$A$5:$A$19,0)),"")) -> N/A | M7: =IF(A7="","",F7*K7) -> 13749.736 | N7: =IF(A7="","",IFERROR(G7*L7,0)) -> 0 | O7: =IF(A7="","",H7*K7) -> 634.61538 | P7: =IF(A7="","",SUM(M7:O7)) -> 14384.351 | Q7: =IF(P7="","",P7*Rates!$B$3) -> 5034.5228 | R7: =IF(P7="","",(P7+Q7)*Rates!$B$4) -> 10680.381 | S7: =IF(P7="","",P7+Q7+R7) -> 30099.254
A8: 123457 | B8: =IF(A8="","",IFERROR(INDEX(Personnel!$B$5:$B$19,MATCH($A8,Personnel!$A$5:$A$19,0)),"-- not found --")) -> Maria Alvarez | C8: =IF(A8="","",IFERROR(INDEX(Personnel!$C$5:$C$19,MATCH($A8,Personnel!$A$5:$A$19,0)),"")) -> Program Manager | D8: 2 | E8: =IF(D8="","",EDATE(Dashboard!$C$5,D8-1)) -> 46054 | F8: 173.33 | G8: 0 | H8: 0 | I8: =IFERROR(IF(OR(A8="",D8=""),"",MAX(0,(INDEX(Personnel!$G$5:$G$19,MATCH($A8,Personnel!$A$5:$A$19,0))/12)*((MIN(EOMONTH(E8,0),IF(INDEX(Personnel!$K$5:$K$19,MATCH($A8,Personnel!$A$5:$A$19,0))="",EOMONTH(E8,0),INDEX(Personnel!$K$5:$K$19,MATCH($A8,Personnel!$A$5:$A$19,0))))-MAX(DATE(YEAR(E8),MONTH(E8),1),INDEX(Personnel!$J$5:$J$19,MATCH($A8,Personnel!$A$5:$A$19,0)))+1)/DAY(EOMONTH(E8,0))))),"") -> 173.33333 | J8: =IF(OR(I8="",A8=""),"",(F8+G8+H8)-I8) -> -0.0033333333 | K8: =IF(A8="","",IFERROR(INDEX(Personnel!$H$5:$H$19,MATCH($A8,Personnel!$A$5:$A$19,0)),"")) -> 79.326923 | L8: =IF(A8="","",IFERROR(INDEX(Personnel!$I$5:$I$19,MATCH($A8,Personnel!$A$5:$A$19,0)),"")) -> N/A | M8: =IF(A8="","",F8*K8) -> 13749.736 | N8: =IF(A8="","",IFERROR(G8*L8,0)) -> 0 | O8: =IF(A8="","",H8*K8) -> 0 | P8: =IF(A8="","",SUM(M8:O8)) -> 13749.736 | Q8: =IF(P8="","",P8*Rates!$B$3) -> 4812.4075 | R8: =IF(P8="","",(P8+Q8)*Rates!$B$4) -> 10209.179 | S8: =IF(P8="","",P8+Q8+R8) -> 28771.322
A9: 123458 | B9: =IF(A9="","",IFERROR(INDEX(Personnel!$B$5:$B$19,MATCH($A9,Personnel!$A$5:$A$19,0)),"-- not found --")) -> Dave Chen | C9: =IF(A9="","",IFERROR(INDEX(Personnel!$C$5:$C$19,MATCH($A9,Personnel!$A$5:$A$19,0)),"")) -> Admin Support | D9: 1 | E9: =IF(D9="","",EDATE(Dashboard!$C$5,D9-1)) -> 46023 | F9: 150 | G9: 12 | H9: 0 | I9: =IFERROR(IF(OR(A9="",D9=""),"",MAX(0,(INDEX(Personnel!$G$5:$G$19,MATCH($A9,Personnel!$A$5:$A$19,0))/12)*((MIN(EOMONTH(E9,0),IF(INDEX(Personnel!$K$5:$K$19,MATCH($A9,Personnel!$A$5:$A$19,0))="",EOMONTH(E9,0),INDEX(Personnel!$K$5:$K$19,MATCH($A9,Personnel!$A$5:$A$19,0))))-MAX(DATE(YEAR(E9),MONTH(E9),1),INDEX(Personnel!$J$5:$J$19,MATCH($A9,Personnel!$A$5:$A$19,0)))+1)/DAY(EOMONTH(E9,0))))),"") -> 173.33333 | J9: =IF(OR(I9="",A9=""),"",(F9+G9+H9)-I9) -> -11.333333 | K9: =IF(A9="","",IFERROR(INDEX(Personnel!$H$5:$H$19,MATCH($A9,Personnel!$A$5:$A$19,0)),"")) -> 28.5 | L9: =IF(A9="","",IFERROR(INDEX(Personnel!$I$5:$I$19,MATCH($A9,Personnel!$A$5:$A$19,0)),"")) -> 42.75 | M9: =IF(A9="","",F9*K9) -> 4275 | N9: =IF(A9="","",IFERROR(G9*L9,0)) -> 513 | O9: =IF(A9="","",H9*K9) -> 0 | P9: =IF(A9="","",SUM(M9:O9)) -> 4788 | Q9: =IF(P9="","",P9*Rates!$B$3) -> 1675.8 | R9: =IF(P9="","",(P9+Q9)*Rates!$B$4) -> 3555.09 | S9: =IF(P9="","",P9+Q9+R9) -> 10018.89
B10: =IF(A10="","",IFERROR(INDEX(Personnel!$B$5:$B$19,MATCH($A10,Personnel!$A$5:$A$19,0)),"-- not found --")) | C10: =IF(A10="","",IFERROR(INDEX(Personnel!$C$5:$C$19,MATCH($A10,Personnel!$A$5:$A$19,0)),"")) | E10: =IF(D10="","",EDATE(Dashboard!$C$5,D10-1)) | I10: =IFERROR(IF(OR(A10="",D10=""),"",MAX(0,(INDEX(Personnel!$G$5:$G$19,MATCH($A10,Personnel!$A$5:$A$19,0))/12)*((MIN(EOMONTH(E10,0),IF(INDEX(Personnel!$K$5:$K$19,MATCH($A10,Personnel!$A$5:$A$19,0))="",EOMONTH(E10,0),INDEX(Personnel!$K$5:$K$19,MATCH($A10,Personnel!$A$5:$A$19,0))))-MAX(DATE(YEAR(E10),MONTH(E10),1),INDEX(Personnel!$J$5:$J$19,MATCH($A10,Personnel!$A$5:$A$19,0)))+1)/DAY(EOMONTH(E10,0))))),"") | J10: =IF(OR(I10="",A10=""),"",(F10+G10+H10)-I10) | K10: =IF(A10="","",IFERROR(INDEX(Personnel!$H$5:$H$19,MATCH($A10,Personnel!$A$5:$A$19,0)),"")) | L10: =IF(A10="","",IFERROR(INDEX(Personnel!$I$5:$I$19,MATCH($A10,Personnel!$A$5:$A$19,0)),"")) | M10: =IF(A10="","",F10*K10) | N10: =IF(A10="","",IFERROR(G10*L10,0)) | O10: =IF(A10="","",H10*K10) | P10: =IF(A10="","",SUM(M10:O10)) | Q10: =IF(P10="","",P10*Rates!$B$3) | R10: =IF(P10="","",(P10+Q10)*Rates!$B$4) | S10: =IF(P10="","",P10+Q10+R10)
B11: =IF(A11="","",IFERROR(INDEX(Personnel!$B$5:$B$19,MATCH($A11,Personnel!$A$5:$A$19,0)),"-- not found --")) | C11: =IF(A11="","",IFERROR(INDEX(Personnel!$C$5:$C$19,MATCH($A11,Personnel!$A$5:$A$19,0)),"")) | E11: =IF(D11="","",EDATE(Dashboard!$C$5,D11-1)) | I11: =IFERROR(IF(OR(A11="",D11=""),"",MAX(0,(INDEX(Personnel!$G$5:$G$19,MATCH($A11,Personnel!$A$5:$A$19,0))/12)*((MIN(EOMONTH(E11,0),IF(INDEX(Personnel!$K$5:$K$19,MATCH($A11,Personnel!$A$5:$A$19,0))="",EOMONTH(E11,0),INDEX(Personnel!$K$5:$K$19,MATCH($A11,Personnel!$A$5:$A$19,0))))-MAX(DATE(YEAR(E11),MONTH(E11),1),INDEX(Personnel!$J$5:$J$19,MATCH($A11,Personnel!$A$5:$A$19,0)))+1)/DAY(EOMONTH(E11,0))))),"") | J11: =IF(OR(I11="",A11=""),"",(F11+G11+H11)-I11) | K11: =IF(A11="","",IFERROR(INDEX(Personnel!$H$5:$H$19,MATCH($A11,Personnel!$A$5:$A$19,0)),"")) | L11: =IF(A11="","",IFERROR(INDEX(Personnel!$I$5:$I$19,MATCH($A11,Personnel!$A$5:$A$19,0)),"")) | M11: =IF(A11="","",F11*K11) | N11: =IF(A11="","",IFERROR(G11*L11,0)) | O11: =IF(A11="","",H11*K11) | P11: =IF(A11="","",SUM(M11:O11)) | Q11: =IF(P11="","",P11*Rates!$B$3) | R11: =IF(P11="","",(P11+Q11)*Rates!$B$4) | S11: =IF(P11="","",P11+Q11+R11)
B12: =IF(A12="","",IFERROR(INDEX(Personnel!$B$5:$B$19,MATCH($A12,Personnel!$A$5:$A$19,0)),"-- not found --")) | C12: =IF(A12="","",IFERROR(INDEX(Personnel!$C$5:$C$19,MATCH($A12,Personnel!$A$5:$A$19,0)),"")) | E12: =IF(D12="","",EDATE(Dashboard!$C$5,D12-1)) | I12: =IFERROR(IF(OR(A12="",D12=""),"",MAX(0,(INDEX(Personnel!$G$5:$G$19,MATCH($A12,Personnel!$A$5:$A$19,0))/12)*((MIN(EOMONTH(E12,0),IF(INDEX(Personnel!$K$5:$K$19,MATCH($A12,Personnel!$A$5:$A$19,0))="",EOMONTH(E12,0),INDEX(Personnel!$K$5:$K$19,MATCH($A12,Personnel!$A$5:$A$19,0))))-MAX(DATE(YEAR(E12),MONTH(E12),1),INDEX(Personnel!$J$5:$J$19,MATCH($A12,Personnel!$A$5:$A$19,0)))+1)/DAY(EOMONTH(E12,0))))),"") | J12: =IF(OR(I12="",A12=""),"",(F12+G12+H12)-I12) | K12: =IF(A12="","",IFERROR(INDEX(Personnel!$H$5:$H$19,MATCH($A12,Personnel!$A$5:$A$19,0)),"")) | L12: =IF(A12="","",IFERROR(INDEX(Personnel!$I$5:$I$19,MATCH($A12,Personnel!$A$5:$A$19,0)),"")) | M12: =IF(A12="","",F12*K12) | N12: =IF(A12="","",IFERROR(G12*L12,0)) | O12: =IF(A12="","",H12*K12) | P12: =IF(A12="","",SUM(M12:O12)) | Q12: =IF(P12="","",P12*Rates!$B$3) | R12: =IF(P12="","",(P12+Q12)*Rates!$B$4) | S12: =IF(P12="","",P12+Q12+R12)
B13: =IF(A13="","",IFERROR(INDEX(Personnel!$B$5:$B$19,MATCH($A13,Personnel!$A$5:$A$19,0)),"-- not found --")) | C13: =IF(A13="","",IFERROR(INDEX(Personnel!$C$5:$C$19,MATCH($A13,Personnel!$A$5:$A$19,0)),"")) | E13: =IF(D13="","",EDATE(Dashboard!$C$5,D13-1)) | I13: =IFERROR(IF(OR(A13="",D13=""),"",MAX(0,(INDEX(Personnel!$G$5:$G$19,MATCH($A13,Personnel!$A$5:$A$19,0))/12)*((MIN(EOMONTH(E13,0),IF(INDEX(Personnel!$K$5:$K$19,MATCH($A13,Personnel!$A$5:$A$19,0))="",EOMONTH(E13,0),INDEX(Personnel!$K$5:$K$19,MATCH($A13,Personnel!$A$5:$A$19,0))))-MAX(DATE(YEAR(E13),MONTH(E13),1),INDEX(Personnel!$J$5:$J$19,MATCH($A13,Personnel!$A$5:$A$19,0)))+1)/DAY(EOMONTH(E13,0))))),"") | J13: =IF(OR(I13="",A13=""),"",(F13+G13+H13)-I13) | K13: =IF(A13="","",IFERROR(INDEX(Personnel!$H$5:$H$19,MATCH($A13,Personnel!$A$5:$A$19,0)),"")) | L13: =IF(A13="","",IFERROR(INDEX(Personnel!$I$5:$I$19,MATCH($A13,Personnel!$A$5:$A$19,0)),"")) | M13: =IF(A13="","",F13*K13) | N13: =IF(A13="","",IFERROR(G13*L13,0)) | O13: =IF(A13="","",H13*K13) | P13: =IF(A13="","",SUM(M13:O13)) | Q13: =IF(P13="","",P13*Rates!$B$3) | R13: =IF(P13="","",(P13+Q13)*Rates!$B$4) | S13: =IF(P13="","",P13+Q13+R13)
B14: =IF(A14="","",IFERROR(INDEX(Personnel!$B$5:$B$19,MATCH($A14,Personnel!$A$5:$A$19,0)),"-- not found --")) | C14: =IF(A14="","",IFERROR(INDEX(Personnel!$C$5:$C$19,MATCH($A14,Personnel!$A$5:$A$19,0)),"")) | E14: =IF(D14="","",EDATE(Dashboard!$C$5,D14-1)) | I14: =IFERROR(IF(OR(A14="",D14=""),"",MAX(0,(INDEX(Personnel!$G$5:$G$19,MATCH($A14,Personnel!$A$5:$A$19,0))/12)*((MIN(EOMONTH(E14,0),IF(INDEX(Personnel!$K$5:$K$19,MATCH($A14,Personnel!$A$5:$A$19,0))="",EOMONTH(E14,0),INDEX(Personnel!$K$5:$K$19,MATCH($A14,Personnel!$A$5:$A$19,0))))-MAX(DATE(YEAR(E14),MONTH(E14),1),INDEX(Personnel!$J$5:$J$19,MATCH($A14,Personnel!$A$5:$A$19,0)))+1)/DAY(EOMONTH(E14,0))))),"") | J14: =IF(OR(I14="",A14=""),"",(F14+G14+H14)-I14) | K14: =IF(A14="","",IFERROR(INDEX(Personnel!$H$5:$H$19,MATCH($A14,Personnel!$A$5:$A$19,0)),"")) | L14: =IF(A14="","",IFERROR(INDEX(Personnel!$I$5:$I$19,MATCH($A14,Personnel!$A$5:$A$19,0)),"")) | M14: =IF(A14="","",F14*K14) | N14: =IF(A14="","",IFERROR(G14*L14,0)) | O14: =IF(A14="","",H14*K14) | P14: =IF(A14="","",SUM(M14:O14)) | Q14: =IF(P14="","",P14*Rates!$B$3) | R14: =IF(P14="","",(P14+Q14)*Rates!$B$4) | S14: =IF(P14="","",P14+Q14+R14)
B15: =IF(A15="","",IFERROR(INDEX(Personnel!$B$5:$B$19,MATCH($A15,Personnel!$A$5:$A$19,0)),"-- not found --")) | C15: =IF(A15="","",IFERROR(INDEX(Personnel!$C$5:$C$19,MATCH($A15,Personnel!$A$5:$A$19,0)),"")) | E15: =IF(D15="","",EDATE(Dashboard!$C$5,D15-1)) | I15: =IFERROR(IF(OR(A15="",D15=""),"",MAX(0,(INDEX(Personnel!$G$5:$G$19,MATCH($A15,Personnel!$A$5:$A$19,0))/12)*((MIN(EOMONTH(E15,0),IF(INDEX(Personnel!$K$5:$K$19,MATCH($A15,Personnel!$A$5:$A$19,0))="",EOMONTH(E15,0),INDEX(Personnel!$K$5:$K$19,MATCH($A15,Personnel!$A$5:$A$19,0))))-MAX(DATE(YEAR(E15),MONTH(E15),1),INDEX(Personnel!$J$5:$J$19,MATCH($A15,Personnel!$A$5:$A$19,0)))+1)/DAY(EOMONTH(E15,0))))),"") | J15: =IF(OR(I15="",A15=""),"",(F15+G15+H15)-I15) | K15: =IF(A15="","",IFERROR(INDEX(Personnel!$H$5:$H$19,MATCH($A15,Personnel!$A$5:$A$19,0)),"")) | L15: =IF(A15="","",IFERROR(INDEX(Personnel!$I$5:$I$19,MATCH($A15,Personnel!$A$5:$A$19,0)),"")) | M15: =IF(A15="","",F15*K15) | N15: =IF(A15="","",IFERROR(G15*L15,0)) | O15: =IF(A15="","",H15*K15) | P15: =IF(A15="","",SUM(M15:O15)) | Q15: =IF(P15="","",P15*Rates!$B$3) | R15: =IF(P15="","",(P15+Q15)*Rates!$B$4) | S15: =IF(P15="","",P15+Q15+R15)
B16: =IF(A16="","",IFERROR(INDEX(Personnel!$B$5:$B$19,MATCH($A16,Personnel!$A$5:$A$19,0)),"-- not found --")) | C16: =IF(A16="","",IFERROR(INDEX(Personnel!$C$5:$C$19,MATCH($A16,Personnel!$A$5:$A$19,0)),"")) | E16: =IF(D16="","",EDATE(Dashboard!$C$5,D16-1)) | I16: =IFERROR(IF(OR(A16="",D16=""),"",MAX(0,(INDEX(Personnel!$G$5:$G$19,MATCH($A16,Personnel!$A$5:$A$19,0))/12)*((MIN(EOMONTH(E16,0),IF(INDEX(Personnel!$K$5:$K$19,MATCH($A16,Personnel!$A$5:$A$19,0))="",EOMONTH(E16,0),INDEX(Personnel!$K$5:$K$19,MATCH($A16,Personnel!$A$5:$A$19,0))))-MAX(DATE(YEAR(E16),MONTH(E16),1),INDEX(Personnel!$J$5:$J$19,MATCH($A16,Personnel!$A$5:$A$19,0)))+1)/DAY(EOMONTH(E16,0))))),"") | J16: =IF(OR(I16="",A16=""),"",(F16+G16+H16)-I16) | K16: =IF(A16="","",IFERROR(INDEX(Personnel!$H$5:$H$19,MATCH($A16,Personnel!$A$5:$A$19,0)),"")) | L16: =IF(A16="","",IFERROR(INDEX(Personnel!$I$5:$I$19,MATCH($A16,Personnel!$A$5:$A$19,0)),"")) | M16: =IF(A16="","",F16*K16) | N16: =IF(A16="","",IFERROR(G16*L16,0)) | O16: =IF(A16="","",H16*K16) | P16: =IF(A16="","",SUM(M16:O16)) | Q16: =IF(P16="","",P16*Rates!$B$3) | R16: =IF(P16="","",(P16+Q16)*Rates!$B$4) | S16: =IF(P16="","",P16+Q16+R16)
B17: =IF(A17="","",IFERROR(INDEX(Personnel!$B$5:$B$19,MATCH($A17,Personnel!$A$5:$A$19,0)),"-- not found --")) | C17: =IF(A17="","",IFERROR(INDEX(Personnel!$C$5:$C$19,MATCH($A17,Personnel!$A$5:$A$19,0)),"")) | E17: =IF(D17="","",EDATE(Dashboard!$C$5,D17-1)) | I17: =IFERROR(IF(OR(A17="",D17=""),"",MAX(0,(INDEX(Personnel!$G$5:$G$19,MATCH($A17,Personnel!$A$5:$A$19,0))/12)*((MIN(EOMONTH(E17,0),IF(INDEX(Personnel!$K$5:$K$19,MATCH($A17,Personnel!$A$5:$A$19,0))="",EOMONTH(E17,0),INDEX(Personnel!$K$5:$K$19,MATCH($A17,Personnel!$A$5:$A$19,0))))-MAX(DATE(YEAR(E17),MONTH(E17),1),INDEX(Personnel!$J$5:$J$19,MATCH($A17,Personnel!$A$5:$A$19,0)))+1)/DAY(EOMONTH(E17,0))))),"") | J17: =IF(OR(I17="",A17=""),"",(F17+G17+H17)-I17) | K17: =IF(A17="","",IFERROR(INDEX(Personnel!$H$5:$H$19,MATCH($A17,Personnel!$A$5:$A$19,0)),"")) | L17: =IF(A17="","",IFERROR(INDEX(Personnel!$I$5:$I$19,MATCH($A17,Personnel!$A$5:$A$19,0)),"")) | M17: =IF(A17="","",F17*K17) | N17: =IF(A17="","",IFERROR(G17*L17,0)) | O17: =IF(A17="","",H17*K17) | P17: =IF(A17="","",SUM(M17:O17)) | Q17: =IF(P17="","",P17*Rates!$B$3) | R17: =IF(P17="","",(P17+Q17)*Rates!$B$4) | S17: =IF(P17="","",P17+Q17+R17)
B18: =IF(A18="","",IFERROR(INDEX(Personnel!$B$5:$B$19,MATCH($A18,Personnel!$A$5:$A$19,0)),"-- not found --")) | C18: =IF(A18="","",IFERROR(INDEX(Personnel!$C$5:$C$19,MATCH($A18,Personnel!$A$5:$A$19,0)),"")) | E18: =IF(D18="","",EDATE(Dashboard!$C$5,D18-1)) | I18: =IFERROR(IF(OR(A18="",D18=""),"",MAX(0,(INDEX(Personnel!$G$5:$G$19,MATCH($A18,Personnel!$A$5:$A$19,0))/12)*((MIN(EOMONTH(E18,0),IF(INDEX(Personnel!$K$5:$K$19,MATCH($A18,Personnel!$A$5:$A$19,0))="",EOMONTH(E18,0),INDEX(Personnel!$K$5:$K$19,MATCH($A18,Personnel!$A$5:$A$19,0))))-MAX(DATE(YEAR(E18),MONTH(E18),1),INDEX(Personnel!$J$5:$J$19,MATCH($A18,Personnel!$A$5:$A$19,0)))+1)/DAY(EOMONTH(E18,0))))),"") | J18: =IF(OR(I18="",A18=""),"",(F18+G18+H18)-I18) | K18: =IF(A18="","",IFERROR(INDEX(Personnel!$H$5:$H$19,MATCH($A18,Personnel!$A$5:$A$19,0)),"")) | L18: =IF(A18="","",IFERROR(INDEX(Personnel!$I$5:$I$19,MATCH($A18,Personnel!$A$5:$A$19,0)),"")) | M18: =IF(A18="","",F18*K18) | N18: =IF(A18="","",IFERROR(G18*L18,0)) | O18: =IF(A18="","",H18*K18) | P18: =IF(A18="","",SUM(M18:O18)) | Q18: =IF(P18="","",P18*Rates!$B$3) | R18: =IF(P18="","",(P18+Q18)*Rates!$B$4) | S18: =IF(P18="","",P18+Q18+R18)
B19: =IF(A19="","",IFERROR(INDEX(Personnel!$B$5:$B$19,MATCH($A19,Personnel!$A$5:$A$19,0)),"-- not found --")) | C19: =IF(A19="","",IFERROR(INDEX(Personnel!$C$5:$C$19,MATCH($A19,Personnel!$A$5:$A$19,0)),"")) | E19: =IF(D19="","",EDATE(Dashboard!$C$5,D19-1)) | I19: =IFERROR(IF(OR(A19="",D19=""),"",MAX(0,(INDEX(Personnel!$G$5:$G$19,MATCH($A19,Personnel!$A$5:$A$19,0))/12)*((MIN(EOMONTH(E19,0),IF(INDEX(Personnel!$K$5:$K$19,MATCH($A19,Personnel!$A$5:$A$19,0))="",EOMONTH(E19,0),INDEX(Personnel!$K$5:$K$19,MATCH($A19,Personnel!$A$5:$A$19,0))))-MAX(DATE(YEAR(E19),MONTH(E19),1),INDEX(Personnel!$J$5:$J$19,MATCH($A19,Personnel!$A$5:$A$19,0)))+1)/DAY(EOMONTH(E19,0))))),"") | J19: =IF(OR(I19="",A19=""),"",(F19+G19+H19)-I19) | K19: =IF(A19="","",IFERROR(INDEX(Personnel!$H$5:$H$19,MATCH($A19,Personnel!$A$5:$A$19,0)),"")) | L19: =IF(A19="","",IFERROR(INDEX(Personnel!$I$5:$I$19,MATCH($A19,Personnel!$A$5:$A$19,0)),"")) | M19: =IF(A19="","",F19*K19) | N19: =IF(A19="","",IFERROR(G19*L19,0)) | O19: =IF(A19="","",H19*K19) | P19: =IF(A19="","",SUM(M19:O19)) | Q19: =IF(P19="","",P19*Rates!$B$3) | R19: =IF(P19="","",(P19+Q19)*Rates!$B$4) | S19: =IF(P19="","",P19+Q19+R19)
B20: =IF(A20="","",IFERROR(INDEX(Personnel!$B$5:$B$19,MATCH($A20,Personnel!$A$5:$A$19,0)),"-- not found --")) | C20: =IF(A20="","",IFERROR(INDEX(Personnel!$C$5:$C$19,MATCH($A20,Personnel!$A$5:$A$19,0)),"")) | E20: =IF(D20="","",EDATE(Dashboard!$C$5,D20-1)) | I20: =IFERROR(IF(OR(A20="",D20=""),"",MAX(0,(INDEX(Personnel!$G$5:$G$19,MATCH($A20,Personnel!$A$5:$A$19,0))/12)*((MIN(EOMONTH(E20,0),IF(INDEX(Personnel!$K$5:$K$19,MATCH($A20,Personnel!$A$5:$A$19,0))="",EOMONTH(E20,0),INDEX(Personnel!$K$5:$K$19,MATCH($A20,Personnel!$A$5:$A$19,0))))-MAX(DATE(YEAR(E20),MONTH(E20),1),INDEX(Personnel!$J$5:$J$19,MATCH($A20,Personnel!$A$5:$A$19,0)))+1)/DAY(EOMONTH(E20,0))))),"") | J20: =IF(OR(I20="",A20=""),"",(F20+G20+H20)-I20) | K20: =IF(A20="","",IFERROR(INDEX(Personnel!$H$5:$H$19,MATCH($A20,Personnel!$A$5:$A$19,0)),"")) | L20: =IF(A20="","",IFERROR(INDEX(Personnel!$I$5:$I$19,MATCH($A20,Personnel!$A$5:$A$19,0)),"")) | M20: =IF(A20="","",F20*K20) | N20: =IF(A20="","",IFERROR(G20*L20,0)) | O20: =IF(A20="","",H20*K20) | P20: =IF(A20="","",SUM(M20:O20)) | Q20: =IF(P20="","",P20*Rates!$B$3) | R20: =IF(P20="","",(P20+Q20)*Rates!$B$4) | S20: =IF(P20="","",P20+Q20+R20)
B21: =IF(A21="","",IFERROR(INDEX(Personnel!$B$5:$B$19,MATCH($A21,Personnel!$A$5:$A$19,0)),"-- not found --")) | C21: =IF(A21="","",IFERROR(INDEX(Personnel!$C$5:$C$19,MATCH($A21,Personnel!$A$5:$A$19,0)),"")) | E21: =IF(D21="","",EDATE(Dashboard!$C$5,D21-1)) | I21: =IFERROR(IF(OR(A21="",D21=""),"",MAX(0,(INDEX(Personnel!$G$5:$G$19,MATCH($A21,Personnel!$A$5:$A$19,0))/12)*((MIN(EOMONTH(E21,0),IF(INDEX(Personnel!$K$5:$K$19,MATCH($A21,Personnel!$A$5:$A$19,0))="",EOMONTH(E21,0),INDEX(Personnel!$K$5:$K$19,MATCH($A21,Personnel!$A$5:$A$19,0))))-MAX(DATE(YEAR(E21),MONTH(E21),1),INDEX(Personnel!$J$5:$J$19,MATCH($A21,Personnel!$A$5:$A$19,0)))+1)/DAY(EOMONTH(E21,0))))),"") | J21: =IF(OR(I21="",A21=""),"",(F21+G21+H21)-I21) | K21: =IF(A21="","",IFERROR(INDEX(Personnel!$H$5:$H$19,MATCH($A21,Personnel!$A$5:$A$19,0)),"")) | L21: =IF(A21="","",IFERROR(INDEX(Personnel!$I$5:$I$19,MATCH($A21,Personnel!$A$5:$A$19,0)),"")) | M21: =IF(A21="","",F21*K21) | N21: =IF(A21="","",IFERROR(G21*L21,0)) | O21: =IF(A21="","",H21*K21) | P21: =IF(A21="","",SUM(M21:O21)) | Q21: =IF(P21="","",P21*Rates!$B$3) | R21: =IF(P21="","",(P21+Q21)*Rates!$B$4) | S21: =IF(P21="","",P21+Q21+R21)
... B124: =IF(A124="","",IFERROR(INDEX(Personnel!$B$5:$B$19,MATCH($A124,Personnel!$A$5:$A$19,0)),"-- not found --")) | C124: =IF(A124="","",IFERROR(INDEX(Personnel!$C$5:$C$19,MATCH($A124,Personnel!$A$5:$A$19,0)),"")) | E124: =IF(D124="","",EDATE(Dashboard!$C$5,D124-1)) | I124: =IFERROR(IF(OR(A124="",D124=""),"",MAX(0,(INDEX(Personnel!$G$5:$G$19,MATCH($A124,Personnel!$A$5:$A$19,0))/12)*((MIN(EOMONTH(E124,0),IF(INDEX(Personnel!$K$5:$K$19,MATCH($A124,Personnel!$A$5:$A$19,0))="",EOMONTH(E124,0),INDEX(Personnel!$K$5:$K$19,MATCH($A124,Personnel!$A$5:$A$19,0))))-MAX(DATE(YEAR(E124),MONTH(E124),1),INDEX(Personnel!$J$5:$J$19,MATCH($A124,Personnel!$A$5:$A$19,0)))+1)/DAY(EOMONTH(E124,0))))),"") | J124: =IF(OR(I124="",A124=""),"",(F124+G124+H124)-I124) | K124: =IF(A124="","",IFERROR(INDEX(Personnel!$H$5:$H$19,MATCH($A124,Personnel!$A$5:$A$19,0)),"")) | L124: =IF(A124="","",IFERROR(INDEX(Personnel!$I$5:$I$19,MATCH($A124,Personnel!$A$5:$A$19,0)),"")) | M124: =IF(A124="","",F124*K124) | N124: =IF(A124="","",IFERROR(G124*L124,0)) | O124: =IF(A124="","",H124*K124) | P124: =IF(A124="","",SUM(M124:O124)) | Q124: =IF(P124="","",P124*Rates!$B$3) | R124: =IF(P124="","",(P124+Q124)*Rates!$B$4) | S124: =IF(P124="","",P124+Q124+R124)
A127: Monthly Rollup (auto)
A128: Month # | B128: Month | C128: Total Fully Burdened Labor $
A129: 1 | B129: =EDATE(Dashboard!$C$5,A129-1) -> 46023 | C129: =SUMIFS($S$5:$S$124,$D$5:$D$124,A129) -> 40118.144
A130: 2 | B130: =EDATE(Dashboard!$C$5,A130-1) -> 46054 | C130: =SUMIFS($S$5:$S$124,$D$5:$D$124,A130) -> 28771.322
A131: 3 | B131: =EDATE(Dashboard!$C$5,A131-1) -> 46082 | C131: =SUMIFS($S$5:$S$124,$D$5:$D$124,A131) -> 0
A132: 4 | B132: =EDATE(Dashboard!$C$5,A132-1) -> 46113 | C132: =SUMIFS($S$5:$S$124,$D$5:$D$124,A132) -> 0
A133: 5 | B133: =EDATE(Dashboard!$C$5,A133-1) -> 46143 | C133: =SUMIFS($S$5:$S$124,$D$5:$D$124,A133) -> 0
A134: 6 | B134: =EDATE(Dashboard!$C$5,A134-1) -> 46174 | C134: =SUMIFS($S$5:$S$124,$D$5:$D$124,A134) -> 0
A135: 7 | B135: =EDATE(Dashboard!$C$5,A135-1) -> 46204 | C135: =SUMIFS($S$5:$S$124,$D$5:$D$124,A135) -> 9054.0865
A136: 8 | B136: =EDATE(Dashboard!$C$5,A136-1) -> 46235 | C136: =SUMIFS($S$5:$S$124,$D$5:$D$124,A136) -> 26155.747
A137: 9 | B137: =EDATE(Dashboard!$C$5,A137-1) -> 46266 | C137: =SUMIFS($S$5:$S$124,$D$5:$D$124,A137) -> 0
A138: 10 | B138: =EDATE(Dashboard!$C$5,A138-1) -> 46296 | C138: =SUMIFS($S$5:$S$124,$D$5:$D$124,A138) -> 0
A139: 11 | B139: =EDATE(Dashboard!$C$5,A139-1) -> 46327 | C139: =SUMIFS($S$5:$S$124,$D$5:$D$124,A139) -> 0
A140: 12 | B140: =EDATE(Dashboard!$C$5,A140-1) -> 46357 | C140: =SUMIFS($S$5:$S$124,$D$5:$D$124,A140) -> 0
A142: Acqlerate · DoD Acquisition Training · acqlerate.com

Sheet ODCs
B1: ODCs | E1: Acqlerate · acqlerate.com
A3: Itemized Log
A4: Date | B4: Category | C4: Description | D4: Month # | E4: Amount $
A5: 46036 | B5: Materials | C5: Replacement network switches (5) | D5: 1 | E5: 14200
A6: 46056 | B6: Equipment | C6: Test bench calibration | D6: 2 | E6: 3100
A7: 46132 | B7: Materials | C7: Spare parts kit | D7: 4 | E7: 8600
B23: LOG TOTAL | E23: =SUM(E5:E22) -> 25900
A25: Monthly Rollup (auto)
A26: Month # | B26: Month | C26: Total ODCs $
A27: 1 | B27: =EDATE(Dashboard!$C$5,A27-1) -> 46023 | C27: =SUMIFS($E$5:$E$22,$D$5:$D$22,A27) -> 14200
A28: 2 | B28: =EDATE(Dashboard!$C$5,A28-1) -> 46054 | C28: =SUMIFS($E$5:$E$22,$D$5:$D$22,A28) -> 3100
A29: 3 | B29: =EDATE(Dashboard!$C$5,A29-1) -> 46082 | C29: =SUMIFS($E$5:$E$22,$D$5:$D$22,A29) -> 0
A30: 4 | B30: =EDATE(Dashboard!$C$5,A30-1) -> 46113 | C30: =SUMIFS($E$5:$E$22,$D$5:$D$22,A30) -> 8600
A31: 5 | B31: =EDATE(Dashboard!$C$5,A31-1) -> 46143 | C31: =SUMIFS($E$5:$E$22,$D$5:$D$22,A31) -> 0
A32: 6 | B32: =EDATE(Dashboard!$C$5,A32-1) -> 46174 | C32: =SUMIFS($E$5:$E$22,$D$5:$D$22,A32) -> 0
A33: 7 | B33: =EDATE(Dashboard!$C$5,A33-1) -> 46204 | C33: =SUMIFS($E$5:$E$22,$D$5:$D$22,A33) -> 0
A34: 8 | B34: =EDATE(Dashboard!$C$5,A34-1) -> 46235 | C34: =SUMIFS($E$5:$E$22,$D$5:$D$22,A34) -> 0
A35: 9 | B35: =EDATE(Dashboard!$C$5,A35-1) -> 46266 | C35: =SUMIFS($E$5:$E$22,$D$5:$D$22,A35) -> 0
A36: 10 | B36: =EDATE(Dashboard!$C$5,A36-1) -> 46296 | C36: =SUMIFS($E$5:$E$22,$D$5:$D$22,A36) -> 0
A37: 11 | B37: =EDATE(Dashboard!$C$5,A37-1) -> 46327 | C37: =SUMIFS($E$5:$E$22,$D$5:$D$22,A37) -> 0
A38: 12 | B38: =EDATE(Dashboard!$C$5,A38-1) -> 46357 | C38: =SUMIFS($E$5:$E$22,$D$5:$D$22,A38) -> 0
A40: Acqlerate · DoD Acquisition Training · acqlerate.com

Sheet Travel
B1: Travel | E1: Acqlerate · acqlerate.com
A3: Itemized Log
A4: Date | B4: Category | C4: Description | D4: Month # | E4: Amount $
A5: 46042 | B5: Airfare | C5: PM — kickoff meeting, NAS Norfolk | D5: 1 | E5: 480
A6: 46042 | B6: Lodging | C6: PM — kickoff meeting, 3 nights | D6: 1 | E6: 610
A7: 46091 | B7: Airfare + Per Diem | C7: Lead Engineer — site visit | D7: 3 | E7: 1150
B23: LOG TOTAL | E23: =SUM(E5:E22) -> 2240
A25: Monthly Rollup (auto)
A26: Month # | B26: Month | C26: Total Travel $
A27: 1 | B27: =EDATE(Dashboard!$C$5,A27-1) -> 46023 | C27: =SUMIFS($E$5:$E$22,$D$5:$D$22,A27) -> 1090
A28: 2 | B28: =EDATE(Dashboard!$C$5,A28-1) -> 46054 | C28: =SUMIFS($E$5:$E$22,$D$5:$D$22,A28) -> 0
A29: 3 | B29: =EDATE(Dashboard!$C$5,A29-1) -> 46082 | C29: =SUMIFS($E$5:$E$22,$D$5:$D$22,A29) -> 1150
A30: 4 | B30: =EDATE(Dashboard!$C$5,A30-1) -> 46113 | C30: =SUMIFS($E$5:$E$22,$D$5:$D$22,A30) -> 0
A31: 5 | B31: =EDATE(Dashboard!$C$5,A31-1) -> 46143 | C31: =SUMIFS($E$5:$E$22,$D$5:$D$22,A31) -> 0
A32: 6 | B32: =EDATE(Dashboard!$C$5,A32-1) -> 46174 | C32: =SUMIFS($E$5:$E$22,$D$5:$D$22,A32) -> 0
A33: 7 | B33: =EDATE(Dashboard!$C$5,A33-1) -> 46204 | C33: =SUMIFS($E$5:$E$22,$D$5:$D$22,A33) -> 0
A34: 8 | B34: =EDATE(Dashboard!$C$5,A34-1) -> 46235 | C34: =SUMIFS($E$5:$E$22,$D$5:$D$22,A34) -> 0
A35: 9 | B35: =EDATE(Dashboard!$C$5,A35-1) -> 46266 | C35: =SUMIFS($E$5:$E$22,$D$5:$D$22,A35) -> 0
A36: 10 | B36: =EDATE(Dashboard!$C$5,A36-1) -> 46296 | C36: =SUMIFS($E$5:$E$22,$D$5:$D$22,A36) -> 0
A37: 11 | B37: =EDATE(Dashboard!$C$5,A37-1) -> 46327 | C37: =SUMIFS($E$5:$E$22,$D$5:$D$22,A37) -> 0
A38: 12 | B38: =EDATE(Dashboard!$C$5,A38-1) -> 46357 | C38: =SUMIFS($E$5:$E$22,$D$5:$D$22,A38) -> 0
A40: Acqlerate · DoD Acquisition Training · acqlerate.com
